<?xml version="1.0" encoding="utf-8"?><i><chatserver>chat.bilibili.com</chatserver><chatid>0</chatid><mission>0</mission><maxlimit>2147483647</maxlimit><state>0</state><app>Core-5.5.4.1738</app><real_name>岁己SUI</real_name><roomid>25788785</roomid><source>k-v</source><d p="0.2220,4,25,16772431,1773933540,0,6606769,1">英国人不会英语？</d>
<d p="1.2620,4,25,14893055,1773933542,0,4184347,2">哈哈</d>
<d p="3.8580,1,25,16777215,1773933543,0,158901105,3">这是天启骑士的幻境</d>
<d p="9.0900,4,25,14893055,1773933549,0,227618,4">按现在的地理 他是法国人【</d>
<d p="10.3530,1,25,16777215,1773933550,0,6084449,5">法国</d>
<d p="11.6680,1,25,16777215,1773933551,0,2225137,6">在法国生活的比较多吧</d>
<d p="12.9600,4,25,14893055,1773933552,0,1604425,7">他是英国人 但是在法国长大</d>
<d p="13.1440,1,25,16777215,1773933553,0,3427592,8">他不是英国人</d>
<d p="15.5560,4,25,14893055,1773933555,0,4184347,9">历史梗</d>
<d p="15.5560,1,25,16777215,1773933556,0,158901105,10">不会说英语的英国国王</d>
<d p="17.0450,4,25,16772431,1773933557,0,6606769,11">哈哈哈哈哈哈哈</d>
<d p="24.8460,4,25,16772431,1773933565,0,6606769,12">是的</d>
<d p="26.1450,4,25,14893055,1773933565,0,34531495,13">草</d>
<d p="27.4470,1,25,16777215,1773933567,0,22155699,14">他是法国人，但是是英格兰国王</d>
<d p="28.5740,4,25,14893055,1773933568,0,227618,15">不是 他说的是诺曼语</d>
<d p="31.1600,4,25,14893055,1773933570,0,1604425,16">当时英语也不是主流语言 都说法语的</d>
<d p="31.1600,4,25,14893055,1773933571,0,604035304,17">是吧</d>
<d p="41.5530,4,25,14893055,1773933581,0,4184347,18">其实当时英国上层也是说法语的多</d>
<d p="55.8590,4,25,14893055,1773933595,0,227618,19">那么早还没呢</d>
<d p="69.0440,4,25,14893055,1773933609,0,34531495,20">给我写一下让我也变一下</d>
<d p="80.7460,4,25,16772431,1773933620,0,6606769,21">我去，城市被修复了</d>
<d p="88.3720,4,25,14893055,1773933629,0,227618,22">则是椿的梦境里吧？</d>
<d p="89.6730,1,25,16777215,1773933629,0,158901105,23">这是天启骑士的环境</d>
<d p="92.2580,1,25,16777215,1773933632,0,2225137,24">楚门的世界</d>
<d p="100.0500,4,25,14893055,1773933640,0,227618,25">这是椿的梦境应该。</d>
<d p="101.5500,4,25,16772431,1773933641,0,6606769,26">看来是的</d>
<d p="104.1500,1,25,14893055,1773933644,0,14279,27">嘘，还没揭露呢，你假装不知道</d>
<d p="106.5610,4,25,14893055,1773933646,0,1604425,28">梦世界</d>
<d p="118.2580,4,25,14893055,1773933658,0,227618,29">[岁己收藏集表情包_妈呀]</d>
<d p="120.8610,4,25,14893055,1773933660,0,1604425,30">你来了</d>
<d p="122.1750,1,25,14893055,1773933662,0,628996143,31">神秘农家乐</d>
<d p="123.6530,4,25,16772431,1773933664,0,6606769,32">闪大哥啊；；</d>
<d p="123.6530,4,25,14893055,1773933664,0,34531495,33">能复活吗</d>
<d p="128.6560,4,25,14893055,1773933668,0,227618,34">能修吗 英雄王</d>
<d p="136.6590,1,25,16777215,1773933676,0,3427592,35">小恩来笑兄弟了</d>
<d p="139.2440,4,25,16772431,1773933679,0,6606769,36">对的</d>
<d p="140.3650,1,25,16777215,1773933680,0,2225137,37">闪闪居然在恩奇都之前死了</d>
<d p="143.1530,1,25,16777215,1773933683,0,9574085,38">挡不住了</d>
<d p="145.7470,4,25,16772431,1773933686,0,6606769,39">防不住</d>
<d p="148.1750,4,25,14893055,1773933688,0,227618,40">挡不住啊</d>
<d p="149.6450,1,25,16777215,1773933690,0,3427592,41">仁至义尽了都</d>
<d p="150.9470,1,25,14893055,1773933691,0,14279,42">不懂，可能太远了发挥不了这么多</d>
<d p="150.9470,1,25,16777215,1773933691,0,3493111961488163,43">挡不住</d>
<d p="158.5720,1,25,16777215,1773933698,0,289245810,44">挡不住</d>
<d p="159.8700,4,25,14893055,1773933699,0,1604425,45">加上他也打不过</d>
<d p="160.0470,4,25,16772431,1773933700,0,6606769,46">不知道了</d>
<d p="162.4540,1,25,16777215,1773933702,0,158901105,47">因为天启骑士克绿毛，他感觉天启骑士来了</d>
<d p="175.4740,4,25,14893055,1773933715,0,1604425,48">他敢现身 就被天启单吃了</d>
<d p="179.3540,1,25,16777215,1773933719,0,6084449,49">机器人他俩打不过</d>
<d p="180.8490,4,25,14893055,1773933720,0,34531495,50">还真是</d>
<d p="181.9570,4,25,14893055,1773933721,0,227618,51">是的吧</d>
<d p="187.3520,4,25,16772431,1773933727,0,6606769,52">我不会再有喜悦了</d>
<d p="188.4550,4,25,14893055,1773933728,0,1604425,53">fate就是相性杀</d>
<d p="189.9490,1,25,16777215,1773933730,0,9574085,54">天启是恩奇都天敌，不敢露面</d>
<d p="191.2470,4,25,16772431,1773933730,0,6606769,55">[岁己收藏集表情包_哈哈]</d>
<d p="193.6640,1,25,16777215,1773933733,0,50149,56">笑哭过</d>
<d p="198.8920,1,25,16777215,1773933739,0,2225137,57">不要怪我，我总是要回家</d>
<d p="199.0510,1,25,14893055,1773933739,0,14279,58">兄弟似了</d>
<d p="217.0530,1,25,16777215,1773933757,0,50149,59">看广告可以复活</d>
<d p="217.2450,1,25,16777215,1773933757,0,3427592,60">可以看广告复活闪大哥</d>
<d p="218.3590,4,25,14893055,1773933759,0,227618,61">修得好吗 英雄王哟</d>
<d p="218.5490,4,25,16772431,1773933758,0,6606769,62">狗狗好懂事啊，去提供情绪价值了</d>
<d p="230.0570,4,25,14893055,1773933770,0,227618,63">好浪费的空间</d>
<d p="233.9820,1,25,16777215,1773933774,0,2225137,64">坏女人我好爱</d>
<d p="237.8600,4,25,14893055,1773933777,0,227618,65">层高十米了吧</d>
<d p="245.8490,4,25,16772431,1773933786,0,6606769,66">三层楼当一层用</d>
<d p="252.1830,4,25,14893055,1773933791,0,1604425,67">你不觉得这个白毛是本片最高颜值吗</d>
<d p="258.6710,4,25,14893055,1773933798,0,227618,68">洗窗帘好痛苦</d>
<d p="262.7460,4,25,16772431,1773933803,0,6606769,69">太美了</d>
<d p="267.7760,4,25,14893055,1773933808,0,1604425,70">还长得和你有点像</d>
<d p="274.2610,1,25,16777215,1773933814,0,289245810,71">详情参见国产吉尔伽美什小故事</d>
<d p="275.5590,1,25,16777215,1773933816,0,8481710,72">啊哈哈</d>
<d p="276.8600,4,25,14893055,1773933816,0,4184347,73">好岁这个角度</d>
<d p="278.1960,4,25,14893055,1773933817,0,227618,74">草</d>
<d p="278.1960,4,25,14893055,1773933818,0,604035304,75">哈哈哈哈</d>
<d p="279.4580,1,25,16777215,1773933820,0,50149,76">？</d>
<d p="280.9500,4,25,14893055,1773933821,0,34531495,77">草</d>
<d p="282.0660,4,25,14893055,1773933822,0,87078921,78">草</d>
<d p="283.5520,4,25,16772431,1773933823,0,6606769,79">[岁己收藏集表情包_哈哈]</d>
<d p="284.6660,4,25,14893055,1773933825,0,1604425,80">内田真礼吗</d>
<d p="287.2860,1,25,16777215,1773933827,0,158901105,81">横飞姬可爱的</d>
<d p="292.6580,4,25,14893055,1773933832,0,385663492,82">怒领工资</d>
<d p="293.7620,1,25,16777215,1773933833,0,2225137,83">老太婆可爱捏</d>
<d p="298.9730,4,25,14893055,1773933838,0,227618,84">[岁己收藏集表情包_哈哈]</d>
<d p="306.9500,4,25,16772431,1773933846,0,6606769,85">hhhhh</d>
<d p="317.1840,4,25,14893055,1773933857,0,227618,86">[岁己收藏集表情包_妈呀]</d>
<d p="318.4700,4,25,14893055,1773933859,0,1604425,87">你喜欢这种声音啊</d>
<d p="321.2450,1,25,14893055,1773933860,0,14279,88">好多修女</d>
<d p="326.4430,1,25,14893055,1773933866,0,14279,89">为什么她们都露大腿</d>
<d p="327.7580,1,25,16777215,1773933868,0,19929984,90">这几个修女好色</d>
<d p="342.0490,4,25,14893055,1773933881,0,34531495,91">我去</d>
<d p="347.0590,4,25,14893055,1773933887,0,227618,92">吓死我了 我以为她要说来玩吧</d>
<d p="357.6440,4,25,14893055,1773933897,0,34531495,93">是人是鬼</d>
<d p="358.7640,4,25,14893055,1773933899,0,227618,94">这就是天启吧</d>
<d p="362.8480,4,25,16772431,1773933903,0,6606769,95">太吓人了</d>
<d p="365.2620,1,25,16777215,1773933905,0,8481710,96">哈哈嗯</d>
<d p="366.7550,4,25,14893055,1773933906,0,34531495,97">还真是</d>
<d p="368.0600,4,25,16772431,1773933908,0,6606769,98">确实诶，像无脸男</d>
<d p="368.0600,4,25,14893055,1773933908,0,34531495,99">有点像</d>
<d p="369.1680,4,25,14893055,1773933909,0,227618,100">还真是</d>
<d p="373.0830,4,25,14893055,1773933913,0,4184347,101">是的</d>
<d p="373.0830,1,25,16777215,1773933913,0,158901105,102">黑的就是天启</d>
<d p="395.3450,1,25,16777215,1773933935,0,3427592,103">战争，死亡，饥荒，瘟疫</d>
<d p="397.7630,4,25,14893055,1773933937,0,1604425,104">不觉得很像一根尾巴吗 毛茸茸的</d>
<d p="400.5460,4,25,14893055,1773933940,0,34531495,105">你说</d>
<d p="404.4450,4,25,16772431,1773933944,0,6606769,106">你说</d>
<d p="405.5620,4,25,14893055,1773933945,0,13429933,107">你问</d>
<d p="405.5620,4,25,14893055,1773933946,0,1604425,108">你说</d>
<d p="407.0520,1,25,14893055,1773933947,0,14279,109">你问</d>
<d p="410.7650,4,25,14893055,1773933950,0,87078921,110">你说</d>
<d p="410.7650,4,25,14893055,1773933950,0,227618,111">。。又？你问吧</d>
<d p="412.0740,4,25,14893055,1773933951,0,4184347,112">干嘛</d>
<d p="413.5490,4,25,16772431,1773933953,0,6606769,113">我怎么会生气呢</d>
<d p="413.5490,4,25,14893055,1773933953,0,34531495,114">是金闪闪</d>
<d p="414.6600,4,25,14893055,1773933955,0,227618,115">吉尔伽美什</d>
<d p="414.8450,1,25,14893055,1773933955,0,14279,116">妈呀……</d>
<d p="415.9580,4,25,14893055,1773933956,0,227618,117">金闪闪</d>
<d p="417.4580,1,25,16777215,1773933957,0,454001293,118">[岁己收藏集表情包_哈哈]</d>
<d p="417.4580,4,25,16772431,1773933958,0,6606769,119">是吉尔伽美什</d>
<d p="418.5740,1,25,16777215,1773933958,0,2225137,120">金闪闪</d>
<d p="418.5740,4,25,14893055,1773933958,0,13429933,121">？金闪闪</d>
<d p="418.5740,4,25,14893055,1773933959,0,87078921,122">吉尔伽美什</d>
<d p="418.5740,4,25,14893055,1773933959,0,1604425,123">是金闪闪啊 宝宝</d>
<d p="418.7480,1,25,14893055,1773933958,0,14279,124">不告诉你了，哼</d>
<d p="418.7480,1,25,16777215,1773933958,0,3427592,125">又来了</d>
<d p="419.8610,1,25,16777215,1773933959,0,10808911,126">[岁己收藏集表情包_哈哈]</d>
<d p="419.8610,4,25,14893055,1773933960,0,40382838,127">我先忍着</d>
<d p="420.0500,4,25,14893055,1773933960,0,34531495,128">草</d>
<d p="423.7620,4,25,14893055,1773933964,0,604035304,129">英雄王是金皮卡</d>
<d p="426.3550,4,25,14893055,1773933966,0,227618,130">[岁己收藏集表情包_哈哈]</d>
<d p="426.5590,1,25,16777215,1773933966,0,3546796261378753,131">？</d>
<d p="426.5590,4,25,16772431,1773933966,0,6606769,132">[岁己收藏集表情包_哈哈]</d>
<d p="427.8570,4,25,14893055,1773933967,0,34531495,133">上次是不是问过了我记得</d>
<d p="427.8570,1,25,16777215,1773933967,0,3427592,134">亚瑟是骑士王</d>
<d p="428.9890,4,25,14893055,1773933968,0,1604425,135">这次的saber是狮心王啊</d>
<d p="430.2670,4,25,14893055,1773933971,0,227618,136">啊我好生气</d>
<d p="433.0530,4,25,14893055,1773933972,0,34531495,137">亚瑟王是女saber</d>
<d p="436.8060,4,25,14893055,1773933976,0,378855235,138">亚瑟王</d>
<d p="436.8060,4,25,14893055,1773933976,0,604035304,139">又是英雄王又是亚瑟王的</d>
<d p="436.9490,4,25,16772431,1773933977,0,6606769,140">亚瑟王是阿尔托莉雅，狮心王是查理</d>
<d p="439.3620,1,25,16777215,1773933979,0,2225137,141">亚瑟王是阿尔托莉雅</d>
<d p="440.8460,4,25,14893055,1773933980,0,7254,142">谁是狮心王</d>
<d p="442.1520,1,25,14893055,1773933982,0,14279,143">征服王是亚历山大大帝，你记住</d>
<d p="443.2640,4,25,14893055,1773933983,0,227618,144">[岁己收藏集表情包_哈哈]</d>
<d p="444.7570,1,25,16777215,1773933984,0,19929984,145">阿我好生气</d>
<d p="444.7570,4,25,14893055,1773933985,0,34531495,146">哈哈哈哈</d>
<d p="451.0580,4,25,14893055,1773933991,0,4184347,147">主播这些人名字只有3个字，昨天你还说三个字的好记一点</d>
<d p="456.2670,4,25,14893055,1773933996,0,604035304,148">考考你那谁是英雄王</d>
<d p="459.0550,4,25,16772431,1773933999,0,6606769,149">三品王是牛肉面</d>
<d p="462.7880,1,25,16777215,1773934002,0,8481710,150">气到乳腺增生了</d>
<d p="464.0630,4,25,14893055,1773934004,0,1604425,151">没事的 宝宝大胆问 不记得还会和你说的</d>
<d p="464.2470,4,25,14893055,1773934003,0,385663492,152">你要看前面的几部就清楚了</d>
<d p="465.5530,1,25,14893055,1773934005,0,14279,153">海贼王是歌尔多罗杰，你记住</d>
<d p="471.8610,4,25,14893055,1773934012,0,227618,154">[岁己收藏集表情包_妈呀]</d>
<d p="478.5460,1,25,16777215,1773934018,0,3427592,155">还有个征服王</d>
<d p="486.1580,4,25,14893055,1773934026,0,1604425,156">他这个牙我真欣赏不来</d>
<d p="491.3660,4,25,14893055,1773934031,0,1604425,157">想送他去洗牙</d>
<d p="492.8480,4,25,16772431,1773934032,0,6606769,158">我去！亚妮</d>
<d p="495.2690,4,25,14893055,1773934034,0,227618,159">每个人都要有故事？</d>
<d p="497.8600,1,25,16777215,1773934038,0,158901105,160">征服王太区了</d>
<d p="506.9840,4,25,14893055,1773934046,0,1604425,161">对 他给编故事了</d>
<d p="510.8670,4,25,14893055,1773934051,0,1604425,162">都强化了</d>
<d p="527.9580,4,25,14893055,1773934067,0,34531495,163">确实</d>
<d p="537.0630,1,25,14893055,1773934077,0,14279,164">小鸟王岁己</d>
<d p="539.4600,4,25,14893055,1773934079,0,1604425,165">作家系就这样 像作者小号</d>
<d p="542.0570,4,25,14893055,1773934082,0,1604425,166">想一出是一出</d>
<d p="542.2560,1,25,16777215,1773934082,0,3427592,167">一本仁之书，一本义之书</d>
<d p="545.9630,4,25,14893055,1773934086,0,227618,168">可惜她不是</d>
<d p="551.1610,4,25,14893055,1773934091,0,4184347,169">不XX就出不去的房间并感</d>
<d p="552.4750,4,25,14893055,1773934092,0,227618,170">[岁己收藏集表情包_妈呀]</d>
<d p="556.5470,4,25,14893055,1773934096,0,34531495,171">草</d>
<d p="564.1600,4,25,14893055,1773934104,0,227618,172">[岁己收藏集表情包_妈呀]</d>
<d p="568.2550,4,25,14893055,1773934108,0,34531495,173">被质疑游手好闲了</d>
<d p="570.8490,4,25,16772431,1773934110,0,6606769,174">草</d>
<d p="573.2600,4,25,14893055,1773934113,0,227618,175">乐</d>
<d p="592.7600,1,25,16777215,1773934133,0,6084449,176">他想夺王位的老弟也叫约翰</d>
<d p="599.4460,4,25,14893055,1773934140,0,34531495,177">妈呀</d>
<d p="608.4070,4,25,14893055,1773934149,0,1604425,178">理查看透了事情的本质</d>
<d p="610.9640,4,25,14893055,1773934150,0,227618,179">这就很难抉择了</d>
<d p="616.3520,4,25,16772431,1773934156,0,6606769,180">亚达哟</d>
<d p="616.3520,4,25,14893055,1773934157,0,34531495,181">会有这种剧情吗</d>
<d p="631.7620,4,25,14893055,1773934171,0,227618,182">整个城市只剩下她了【</d>
<d p="638.4560,4,25,16772431,1773934178,0,6606769,183">我去！</d>
<d p="642.1600,1,25,16777215,1773934182,0,2225137,184">我去这么牛</d>
<d p="647.5490,4,25,16772431,1773934187,0,6606769,185">这个也太有b格了</d>
<d p="650.1510,4,25,14893055,1773934190,0,34531495,186">妈呀这也太反派登场</d>
<d p="654.0480,4,25,14893055,1773934193,0,1673559,187">我去 </d>
<d p="657.7670,4,25,14893055,1773934197,0,227618,188">天启这出场压迫力有点高</d>
<d p="673.3790,4,25,14893055,1773934213,0,227618,189">那人家可以变大变小嘛</d>
<d p="676.1500,4,25,16772431,1773934216,0,6606769,190">被小女孩治愈了吧(</d>
<d p="689.1470,1,25,14893055,1773934229,0,14279,191">我在炉石传说里见过</d>
<d p="696.9570,4,25,14893055,1773934236,0,34531495,192">他真是有演讲天赋的</d>
<d p="699.5570,1,25,16777215,1773934240,0,9574085,193">塔塔开</d>
<d p="704.7480,4,25,14893055,1773934244,0,7254,194">[岁己收藏集表情包_哈哈]</d>
<d p="706.0470,1,25,16777215,1773934246,0,22155699,195">天启骑士一般人召不来，只有迷途的羔羊和灭世恶人可以</d>
<d p="720.1590,4,25,14893055,1773934261,0,227618,196">？她看到啥了</d>
<d p="739.8510,4,25,16772431,1773934280,0,6606769,197">[岁己收藏集表情包_啵啵]</d>
<d p="742.4510,4,25,14893055,1773934282,0,34531495,198">妈呀</d>
<d p="747.4780,4,25,14893055,1773934288,0,1604425,199">天启召唤条件是纯粹 纯善或者纯恶</d>
<d p="747.6670,4,25,16772431,1773934288,0,6606769,200">不清楚了</d>
<d p="753.9610,4,25,14893055,1773934294,0,227618,201">定期替换。</d>
<d p="763.0620,4,25,14893055,1773934303,0,227618,202">还带版本更新的</d>
<d p="771.0470,4,25,14893055,1773934310,0,34531495,203">复活了吗要</d>
<d p="780.1580,4,25,16772431,1773934320,0,6606769,204">恩奇都出手了</d>
<d p="781.2820,4,25,14893055,1773934321,0,227618,205">天之锁？</d>
<d p="787.9500,4,25,14893055,1773934328,0,34531495,206">是哦</d>
<d p="803.5540,1,25,14893055,1773934344,0,14279,207">这个魔法阵是连接虚拟与现实吗？</d>
<d p="808.5690,4,25,14893055,1773934348,0,227618,208">草</d>
<d p="808.7480,1,25,14893055,1773934349,0,14279,209">virtual to real</d>
<d p="810.0500,4,25,16772431,1773934349,0,6606769,210">这都可以</d>
<d p="812.4610,4,25,14893055,1773934352,0,227618,211">方便的魔法</d>
<d p="813.9540,4,25,14893055,1773934354,0,34531495,212">妈呀</d>
<d p="821.5670,4,25,14893055,1773934361,0,227618,213">小红帽；；</d>
<d p="821.7610,4,25,14893055,1773934361,0,1673559,214">omg</d>
<d p="821.7610,4,25,16772431,1773934361,0,6606769,215">小红帽又来了</d>
<d p="821.7610,1,25,14893055,1773934361,0,14279,216">虚拟的0和1，也许并不够温暖</d>
<d p="824.3600,1,25,16777215,1773934365,0,3427592,217">小岁戴着小红帽来了</d>
<d p="846.2680,1,25,14893055,1773934386,0,628996143,218">这个魔术是不是叫做virtual to live</d>
<d p="851.6510,4,25,14893055,1773934391,0,34531495,219">妈呀</d>
<d p="856.8610,4,25,14893055,1773934397,0,34531495,220">太爱了你们</d>
<d p="856.8610,4,25,16772431,1773934397,0,6606769,221">[岁己收藏集表情包_哈哈]</d>
<d p="861.8790,1,25,16777215,1773934402,0,2225137,222">你来你来</d>
<d p="861.8790,4,25,14893055,1773934402,0,227618,223">[岁己收藏集表情包_妈呀]</d>
<d p="863.1670,4,25,14893055,1773934403,0,40382838,224">他们是要谈恋爱了吗</d>
<d p="863.3490,4,25,16772431,1773934403,0,6606769,225">我来吧我来</d>
<d p="864.4660,4,25,14893055,1773934405,0,604035304,226">好爱啊</d>
<d p="865.7810,1,25,16777215,1773934406,0,10808911,227">[岁己收藏集表情包_哈哈]</d>
<d p="865.9520,4,25,14893055,1773934406,0,34531495,228">哈哈哈哈</d>
<d p="867.0670,4,25,14893055,1773934407,0,87078921,229">你来</d>
<d p="868.3750,4,25,14893055,1773934408,0,227618,230">我来我来</d>
<d p="871.1520,4,25,14893055,1773934411,0,34531495,231">还真是</d>
<d p="872.4500,1,25,16777215,1773934412,0,454001293,232">[岁己收藏集表情包_哈哈]</d>
<d p="878.7640,4,25,14893055,1773934419,0,604035304,233">还是我来吧我来</d>
<d p="885.2630,4,25,14893055,1773934425,0,1604425,234">天启其实是人机</d>
<d p="889.1840,4,25,14893055,1773934429,0,1604425,235">比豆包还笨</d>
<d p="893.2620,4,25,16772431,1773934433,0,6606769,236">又想起来了</d>
<d p="895.6620,4,25,14893055,1773934435,0,604035304,237">触发关键词了</d>
<d p="895.8540,4,25,14893055,1773934435,0,34531495,238">谁</d>
<d p="902.1650,4,25,14893055,1773934441,0,227618,239">啊？</d>
<d p="903.6550,4,25,14893055,1773934444,0,34531495,240">你还在阿？</d>
<d p="907.5480,4,25,14893055,1773934448,0,34531495,241">你主人不是死了吗</d>
<d p="908.8480,4,25,16772431,1773934449,0,6606769,242">啊？这家伙也在</d>
<d p="909.9780,4,25,14893055,1773934450,0,227618,243">刻耳贝洛斯</d>
<d p="916.4860,4,25,14893055,1773934456,0,604035304,244">大白天就来了</d>
<d p="916.4860,4,25,14893055,1773934457,0,1604425,245">你还活着啊？</d>
<d p="916.6470,4,25,16772431,1773934456,0,6606769,246">这家伙是地狱的，不会死吧</d>
<d p="919.0620,4,25,14893055,1773934459,0,227618,247">那这是梦境</d>
<d p="921.8510,4,25,14893055,1773934461,0,258865753,248">梦里啥都有</d>
<d p="925.5810,4,25,14893055,1773934465,0,87827340,249">这怎么也有三头犬</d>
<d p="929.4910,4,25,14893055,1773934469,0,13429933,250">这对吗</d>
<d p="937.2720,4,25,14893055,1773934476,0,227618,251">说不定只是截取的片段</d>
<d p="943.9470,4,25,16772431,1773934484,0,6606769,252">这是什么</d>
<d p="953.0520,1,25,14893055,1773934493,0,14279,253">绿毛吧</d>
<d p="959.3620,4,25,14893055,1773934499,0,227618,254">又是新人物？</d>
<d p="964.7530,4,25,14893055,1773934504,0,34531495,255">草</d>
<d p="976.2720,4,25,14893055,1773934516,0,1604425,256">因为没被复制进去</d>
<d p="977.7480,1,25,16777215,1773934517,0,9574085,257"> 闪闪死透了</d>
<d p="978.8870,1,25,16777215,1773934518,0,2225137,258">何意味</d>
<d p="978.8870,4,25,14893055,1773934519,0,227618,259">啊？</d>
<d p="979.0520,4,25,16772431,1773934519,0,6606769,260">这个是幻境里，金闪闪在现实中吧</d>
<d p="987.9910,4,25,14893055,1773934527,0,604035304,261">闪闪没在里面吧</d>
<d p="992.0520,4,25,16772431,1773934532,0,6606769,262">啊？</d>
<d p="995.9500,4,25,14893055,1773934535,0,258865753,263">金闪闪命中注定有此一劫</d>
<d p="998.3690,4,25,14893055,1773934538,0,227618,264">emmm</d>
<d p="998.5470,4,25,16772431,1773934538,0,6606769,265">是的，头发颜色也不一样</d>
<d p="999.8500,1,25,14893055,1773934540,0,14279,266">我去，有复制人</d>
<d p="1000.9740,4,25,14893055,1773934541,0,1604425,267">其实是黑发</d>
<d p="1003.7470,4,25,16772431,1773934543,0,6606769,268">我滴妈呀，什么情况</d>
<d p="1007.6480,4,25,14893055,1773934547,0,258865753,269">哇哦看得好仔细</d>
<d p="1010.0680,4,25,14893055,1773934550,0,604035304,270">还有吗</d>
<d p="1011.5510,4,25,14893055,1773934552,0,34531495,271">再看看</d>
<d p="1013.9660,4,25,14893055,1773934554,0,13429933,272">烧烤一下</d>
<d p="1019.3540,4,25,16772431,1773934559,0,6606769,273">还剩好多，绝对有问题</d>
<d p="1028.2780,4,25,14893055,1773934568,0,227618,274">这是PV吧？</d>
<d p="1030.8610,1,25,16777215,1773934570,0,8481710,275">打call</d>
<d p="1031.0490,4,25,14893055,1773934570,0,34531495,276">草</d>
<d p="1032.3480,1,25,14893055,1773934572,0,14279,277">这是啥</d>
<d p="1033.4630,4,25,14893055,1773934573,0,13429933,278">后面不是</d>
<d p="1033.6510,4,25,14893055,1773934574,0,258865753,279">没了吧</d>
<d p="1036.0690,4,25,14893055,1773934576,0,604035304,280">这个是pv</d>
<d p="1039.9710,4,25,14893055,1773934580,0,227618,281">估计是过审对策</d>
<d p="1042.5840,4,25,14893055,1773934582,0,604035304,282">这是第几集了</d>
<d p="1042.7480,4,25,16772431,1773934583,0,6606769,283">啥情况？两次op?</d>
<d p="1046.6520,4,25,14893055,1773934586,0,34531495,284">原来已经看完了吗</d>
<d p="1054.2770,4,25,14893055,1773934594,0,378855235,285">没了</d>
<d p="1055.7520,4,25,14893055,1773934596,0,34531495,286">oh no</d>
<d p="1057.0510,4,25,14893055,1773934597,0,258865753,287">ohno</d>
<d p="1059.4590,1,25,16777215,1773934600,0,8481710,288">欧漏</d>
<d p="1060.7690,4,25,14893055,1773934600,0,1604425,289">目前只有这么多了</d>
<d p="1060.7690,4,25,14893055,1773934601,0,227618,290">啊 就没了</d>
<d p="1060.9560,4,25,16772431,1773934601,0,6606769,291">中幻境了；；</d>
<d p="1060.9560,4,25,14893055,1773934601,0,34531495,292">好看的还是</d>
<d p="1060.9560,1,25,14893055,1773934601,0,14279,293">那咋办</d>
<d p="1062.0650,1,25,16777215,1773934601,0,8481710,294">那怎么办</d>
<d p="1063.5530,4,25,14893055,1773934604,0,22389880,295">[岁己收藏集表情包_凝视]</d>
<d p="1064.6710,1,25,16777215,1773934604,0,2225137,296">我们看学问猫吉尔伽美什的故事吧</d>
<d p="1064.8560,1,25,16777215,1773934605,0,3427592,297">爽了</d>
<d p="1066.1490,4,25,16772431,1773934606,0,6606769,298">oh no，怎么这样</d>
<d p="1067.4570,4,25,14893055,1773934607,0,258865753,299">等跟新了</d>
<d p="1068.7580,4,25,14893055,1773934609,0,14910777,300">[岁己收藏集表情包_哭死]</d>
<d p="1070.0540,4,25,16772431,1773934610,0,6606769,301">天呐；；</d>
<d p="1071.1680,4,25,14893055,1773934611,0,227618,302">应该还剩两集没更新</d>
<d p="1071.3480,1,25,14893055,1773934611,0,14279,303">小岁，今天出了那个，我们看吗，跟上第一梯队</d>
<d p="1072.4640,4,25,14893055,1773934612,0,87078921,304">；；</d>
<d p="1075.2520,4,25,14893055,1773934615,0,34531495,305">有的等了这个</d>
<d p="1075.2520,1,25,16777215,1773934615,0,454001293,306">我还要看</d>
<d p="1077.6790,4,25,14893055,1773934618,0,604035304,307">等一段时间再看后面的吧</d>
<d p="1081.5630,1,25,16777215,1773934622,0,8481710,308">我晕</d>
<d p="1081.7610,1,25,14893055,1773934622,0,14279,309">小岁我们看学问猫吉尔伽美什吧</d>
<d p="1084.3500,4,25,16772431,1773934624,0,6606769,310">是的，jojo</d>
<d p="1086.7730,4,25,14893055,1773934626,0,604035304,311">看一集吧</d>
<d p="1088.0620,4,25,14893055,1773934628,0,227618,312">[岁己收藏集表情包_妈呀]</d>
<d p="1090.6820,1,25,16777215,1773934631,0,8481710,313">福利连什么时候更新</d>
<d p="1091.9670,4,25,14893055,1773934632,0,604035304,314">jojo就一集</d>
<d p="1091.9670,1,25,16777215,1773934632,0,289245810,315">第一集评价还不错的</d>
<d p="1094.5620,1,25,16777215,1773934635,0,20094643,316">我支持jojo</d>
<d p="1094.7570,1,25,14893055,1773934635,0,14279,317">JOJO不一样，第七季重启了</d>
<d p="1097.3500,4,25,14893055,1773934637,0,34531495,318">看你想看的</d>
<d p="1098.4730,1,25,16777215,1773934638,0,10808911,319">就一集 看看吧</d>
<d p="1098.6470,4,25,16772431,1773934639,0,6606769,320">jojo的话，是一次性出完还是只有一集</d>
<d p="1102.3740,4,25,14893055,1773934642,0,604035304,321">jojo先更新了一集</d>
<d p="1102.3740,4,25,14893055,1773934642,0,227618,322">jojo一集47分钟好像</d>
<d p="1103.6820,4,25,14893055,1773934643,0,13429933,323">看你</d>
<d p="1107.7490,4,25,16772431,1773934647,0,6606769,324">jojo只有一集的话，不如攒攒呢</d>
<d p="1108.8780,1,25,16777215,1773934648,0,2225137,325">小岁我们看学问猫吉尔伽美什的故事吧</d>
<d p="1112.9490,4,25,14893055,1773934653,0,34531495,326">不知道，我没看过</d>
<d p="1114.2500,1,25,14893055,1773934654,0,14279,327">就是和之前都不是一个世界了</d>
<d p="1115.3640,4,25,14893055,1773934655,0,1604425,328">芙莉莲出了八集吧</d>
<d p="1116.7160,1,25,16777215,1773934656,0,10808911,329">新宇宙了</d>
<d p="1119.2650,4,25,14893055,1773934659,0,604035304,330">全新世界观了</d>
<d p="1119.4490,4,25,14893055,1773934659,0,258865753,331">你开始看第二季了吗</d>
<d p="1120.7530,1,25,16777215,1773934660,0,3427592,332">名字一样</d>
<d p="1120.7530,1,25,14893055,1773934661,0,14279,333">听说第一集是那种超长片</d>
<d p="1121.8920,4,25,14893055,1773934662,0,227618,334">[岁己收藏集表情包_哈哈]</d>
<d p="1123.1720,4,25,14893055,1773934663,0,87078921,335">重写了一个世界观</d>
<d p="1124.4750,1,25,16777215,1773934664,0,289245810,336">第七季是荒野大镖客</d>
<d p="1127.0610,1,25,16777215,1773934666,0,2225137,337">这个最近好火的</d>
<d p="1129.8500,1,25,14893055,1773934669,0,14279,338">学问猫吉尔伽美什很火，海子姐狂看</d>
<d p="1130.9870,4,25,14893055,1773934670,0,227618,339">不一样</d>
<d p="1130.9870,1,25,16777215,1773934670,0,10808911,340">是的</d>
<d p="1130.9870,4,25,14893055,1773934671,0,604035304,341">jo7是平行世界全新世界观</d>
<d p="1133.7490,4,25,16772431,1773934673,0,6606769,342">就是，jojo7是新的世界，新的知识</d>
<d p="1136.1790,4,25,14893055,1773934676,0,13429933,343">[岁己收藏集表情包_哈哈]</d>
<d p="1136.1790,1,25,16777215,1773934677,0,20094643,344">学问猫看看，</d>
<d p="1136.3590,4,25,16772431,1773934676,0,6606769,345">新的世界</d>
<d p="1141.4090,4,25,14893055,1773934681,0,227618,346">第二季我们不是只看了一集吗</d>
<d p="1141.5490,4,25,16772431,1773934681,0,6606769,347">新的人物</d>
<d p="1142.6670,1,25,16777215,1773934682,0,339001,348">哈哈嗯</d>
<d p="1144.1570,4,25,14893055,1773934684,0,258865753,349">老了</d>
<d p="1144.1570,4,25,14893055,1773934684,0,14910777,350">[岁己收藏集表情包_哈哈]</d>
<d p="1146.5710,1,25,16777215,1773934687,0,10808911,351">几集？</d>
<d p="1147.8700,4,25,14893055,1773934688,0,1604425,352">第七部是重启世界观</d>
<d p="1149.1660,1,25,16777215,1773934688,0,2225137,353">学问猫那个看了你就懂了金闪闪了</d>
<d p="1149.3560,4,25,14893055,1773934689,0,258865753,354">记性不好</d>
<d p="1150.4630,4,25,14893055,1773934690,0,604035304,355">jo7是评价最好的jojo</d>
<d p="1150.6470,1,25,16777215,1773934690,0,19929984,356">别逗，小岁自己记得多少剧情</d>
<d p="1151.7790,1,25,16777215,1773934691,0,20094643,357">看完刚好下播</d>
<d p="1157.1490,4,25,14893055,1773934697,0,34531495,358">不用了解之前的话感觉还行吧</d>
<d p="1158.2620,4,25,14893055,1773934698,0,227618,359">[岁己收藏集表情包_哈哈]</d>
<d p="1159.5620,4,25,14893055,1773934700,0,1604425,360">jo7我有全套漫画</d>
<d p="1160.8730,4,25,14893055,1773934701,0,13429933,361">jojo粉肯定说好看</d>
<d p="1162.1600,1,25,16777215,1773934702,0,8481710,362">问号</d>
<d p="1162.3490,1,25,14893055,1773934702,0,14279,363">你不看我就偷偷看了，你永远失去了和我一起初见的机会</d>
<d p="1167.4090,4,25,14893055,1773934707,0,87078921,364">7的剧情很好看</d>
<d p="1167.4090,4,25,14893055,1773934707,0,604035304,365">好看的jo7</d>
<d p="1170.1540,4,25,14893055,1773934710,0,258865753,366">我去</d>
<d p="1171.4490,1,25,16777215,1773934712,0,3427592,367">睡觉觉了</d>
<d p="1172.7550,4,25,14893055,1773934712,0,34531495,368">哈哈哈哈哈</d>
<d p="1175.1870,1,25,16777215,1773934714,0,10808911,369">[岁己收藏集表情包_哈哈]</d>
<d p="1175.1870,4,25,14893055,1773934716,0,604035304,370">哇哇哇</d>
<d p="1176.4810,4,25,14893055,1773934716,0,227618,371">[岁己收藏集表情包_妈呀]</d>
<d p="1177.9610,4,25,16772431,1773934717,0,6606769,372">我觉得先看什么结构吧，如果是只有一集可以攒一下，之后看个爽</d>
<d p="1179.2530,4,25,14893055,1773934720,0,12052692,373">小岁姐姐晚上好 刚开完会[爱][爱][爱]</d>
<d p="1180.3630,1,25,16777215,1773934720,0,2225137,374">走，带我一个</d>
<d p="1184.2630,4,25,14893055,1773934725,0,4184347,375">已老实</d>
<d p="1184.4520,4,25,14893055,1773934724,0,34531495,376">你来我家我给你买</d>
<d p="1184.4520,1,25,14893055,1773934725,0,14279,377">吉尔伽美什学问猫，只有10分钟，看看嘛</d>
<d p="1185.7480,4,25,14893055,1773934726,0,258865753,378">肘</d>
<d p="1188.1740,4,25,14893055,1773934728,0,1604425,379">妈呀</d>
<d p="1190.7630,4,25,14893055,1773934731,0,227618,380">那应该是</d>
<d p="1192.2520,1,25,16777215,1773934732,0,3427592,381">怎么还有辣妹JK去宅男家看漫画的剧情</d>
<d p="1196.1570,4,25,16772431,1773934736,0,6606769,382">确实，jo7讲的是牛仔的故事</d>
<d p="1199.8810,4,25,14893055,1773934739,0,1604425,383">又想起岁己说的那个辣妹来家里看漫画的了</d>
<d p="1199.8810,4,25,14893055,1773934739,0,604035304,384">在jojo里也是公认最好看的一部</d>
<d p="1206.3700,4,25,14893055,1773934746,0,227618,385">？</d>
<d p="1210.4590,4,25,14893055,1773934750,0,9669499,386">你不是？</d>
<d p="1213.0570,4,25,14893055,1773934752,0,288811455,387">我是 </d>
<d p="1213.0570,4,25,14893055,1773934753,0,12052692,388">肯定不是p话</d>
<d p="1213.0570,4,25,14893055,1773934753,0,34531495,389">你是辣妹jk吗，我可以是</d>
<d p="1219.3630,4,25,14893055,1773934760,0,604035304,390">一起看反击的巨兽</d>
<d p="1220.6820,4,25,14893055,1773934760,0,1604425,391">jo7最精彩</d>
<d p="1222.1550,4,25,14893055,1773934762,0,258865753,392">人不能</d>
<d p="1222.1550,4,25,16772431,1773934762,0,6606769,393">jo7的故事很精彩</d>
<d p="1224.7810,4,25,14893055,1773934764,0,12052692,394">jo7好看的</d>
<d p="1224.7810,1,25,14893055,1773934764,0,14279,395">jo1 jo2你都没看吧</d>
<d p="1227.1670,1,25,16777215,1773934766,0,2225137,396">原来我是辣妹</d>
<d p="1228.4790,4,25,14893055,1773934768,0,227618,397">[岁己收藏集表情包_哈哈]</d>
<d p="1228.4790,4,25,14893055,1773934769,0,87078921,398">jo7的真的好看</d>
<d p="1228.4790,1,25,16777215,1773934769,0,289245810,399">不是 jo7是整个系列的巅峰</d>
<d p="1228.6490,4,25,14893055,1773934768,0,34531495,400">那还不至于的</d>
<d p="1232.5510,4,25,16772431,1773934772,0,6606769,401">草</d>
<d p="1233.6720,4,25,14893055,1773934774,0,13429933,402">[岁己收藏集表情包_哈哈]</d>
<d p="1236.4520,1,25,16777215,1773934776,0,3427592,403">JO3是开拓者</d>
<d p="1238.8660,4,25,14893055,1773934779,0,227618,404">真不一定 开会主要是沟通协调</d>
<d p="1238.8660,1,25,16777215,1773934779,0,8481710,405">真的假的</d>
<d p="1241.4680,4,25,14893055,1773934781,0,1604425,406">我个人最喜欢顺序是7 5 3 4 2 8 16</d>
<d p="1242.9500,4,25,14893055,1773934782,0,34531495,407">有些安全相关的会确实是很必要的</d>
<d p="1246.8490,4,25,16772431,1773934786,0,6606769,408">[岁己收藏集表情包_哈哈]</d>
<d p="1248.1530,4,25,14893055,1773934787,0,258865753,409">不得不看了这下</d>
<d p="1248.1530,4,25,14893055,1773934788,0,9669499,410">JO6是不是要给小岁看睡着了</d>
<d p="1253.3540,4,25,14893055,1773934793,0,12052692,411">7是神</d>
<d p="1257.0670,4,25,14893055,1773934797,0,604035304,412">原作上了青年杂志连载后剧情深度也提升了</d>
<d p="1258.5500,4,25,16772431,1773934799,0,6606769,413">jo7的故事很紧凑的，也是公路片，挺不错的</d>
<d p="1259.6700,4,25,14893055,1773934799,0,227618,414">[岁己收藏集表情包_妈呀]</d>
<d p="1267.6480,4,25,16772431,1773934808,0,6606769,415">jo6我也不太喜欢，过了就过了</d>
<d p="1275.4530,4,25,14893055,1773934816,0,12052692,416">jo6就剩几集没看完 岁己真坏 气我一辈子</d>
<d p="1276.7490,1,25,14893055,1773934816,0,14279,417">JO6越狱之后也挺好看的，可惜中间不好看被岁己一脚踢开了</d>
<d p="1280.4630,4,25,14893055,1773934820,0,604035304,418">jo6是在8之前是系列垫底的</d>
<d p="1280.6600,4,25,14893055,1773934820,0,34531495,419">感觉现在没什么这种作品了</d>
<d p="1281.7970,4,25,14893055,1773934821,0,1604425,420">第七部改成月刊连载了 质量高了很多</d>
<d p="1281.9480,4,25,14893055,1773934822,0,9669499,421">jo6就剩几集没看完 岁己真坏 气我一辈子</d>
<d p="1284.3680,4,25,14893055,1773934824,0,227618,422">星际牛仔结局我也舍不得……可是</d>
<d p="1288.4610,4,25,14893055,1773934829,0,22389880,423">小岁听说黑契不错</d>
<d p="1288.4610,1,25,14893055,1773934829,0,14279,424">那我们来看学问猫吉尔伽美什吧</d>
<d p="1289.7520,4,25,16772431,1773934830,0,6606769,425">对的</d>
<d p="1296.0760,1,25,16777215,1773934836,0,10808911,426">巨人</d>
<d p="1297.5490,1,25,16777215,1773934837,0,3427592,427">也就仅仅第一季了</d>
<d p="1299.9640,4,25,14893055,1773934840,0,87078921,428">是的，可惜第二季拉了</d>
<d p="1303.8780,1,25,16777215,1773934844,0,2225137,429">居然</d>
<d p="1304.0560,4,25,14893055,1773934844,0,288811455,430">那我必须让主播看完psycho pass</d>
<d p="1304.0560,4,25,16772431,1773934844,0,6606769,431">[岁己收藏集表情包_笑了]</d>
<d p="1304.0560,4,25,14893055,1773934844,0,34531495,432">还是悬疑阿</d>
<d p="1306.4850,4,25,14893055,1773934846,0,227618,433">[岁己收藏集表情包_哈哈]</d>
<d p="1306.4850,1,25,16777215,1773934846,0,2225137,434">巨人</d>
<d p="1310.3790,4,25,14893055,1773934850,0,227618,435">第二季拉了</d>
<d p="1311.6670,4,25,14893055,1773934851,0,604035304,436">梦幻岛逃出去后就没看了</d>
<d p="1311.6670,4,25,14893055,1773934851,0,1604425,437">那真该看jo7了</d>
<d p="1313.1540,4,25,14893055,1773934853,0,9669499,438">哈哈嗯</d>
<d p="1316.9140,1,25,16777215,1773934857,0,8481710,439">神作太少了</d>
<d p="1317.0530,4,25,16772431,1773934856,0,6606769,440">来自深渊也是神了</d>
<d p="1322.0750,4,25,14893055,1773934862,0,4184347,441">来自深渊好看</d>
<d p="1323.3710,4,25,14893055,1773934863,0,227618,442">来自深渊感觉都可以啊 可以往后看呢</d>
<d p="1323.3710,1,25,16777215,1773934864,0,10808911,443">[岁己收藏集表情包_哈哈]</d>
<d p="1324.6750,4,25,14893055,1773934864,0,1604425,444">有点猎奇了 对我来说 看那个很难受</d>
<d p="1325.9650,1,25,16772431,1773934866,0,257596619,445">奇巧计程车好看</d>
<d p="1328.5700,1,25,16777215,1773934868,0,339001,446">哈哈嗯</d>
<d p="1329.8750,4,25,14893055,1773934870,0,1604425,447">来自深圳我看不下去</d>
<d p="1331.1750,4,25,14893055,1773934871,0,604035304,448">还是扯到巨人了</d>
<d p="1331.3650,4,25,14893055,1773934871,0,34531495,449">都是我不看动漫之后出的了</d>
<d p="1331.3650,4,25,16772431,1773934871,0,6606769,450">兽娘动物园第一季也不错</d>
<d p="1331.3650,1,25,16777215,1773934872,0,3427592,451">看过86了吗，不存在的战区</d>
<d p="1332.4710,1,25,16777215,1773934872,0,10808911,452">·巨p真的是</d>
<d p="1333.9560,1,25,14893055,1773934873,0,14279,453">学问猫学问猫</d>
<d p="1337.8570,4,25,16772431,1773934878,0,6606769,454">[岁己收藏集表情包_哈哈]</d>
<d p="1338.9940,4,25,14893055,1773934878,0,4184347,455">来自深渊我们差不多3年前看的了是不是</d>
<d p="1340.4540,4,25,14893055,1773934880,0,266375,456">[岁己收藏集表情包_啵啵]</d>
<d p="1342.8860,1,25,16777215,1773934883,0,8481710,457">我还是喜欢看点欢乐的</d>
<d p="1343.0520,1,25,14893055,1773934883,0,14279,458">奇巧出租车最无敌了</d>
<d p="1345.6680,4,25,14893055,1773934885,0,34531495,459">这几个我都没看过，出这些的时候我已经不太看动漫了</d>
<d p="1345.6690,4,25,14893055,1773934886,0,9669499,460">我们来看攻壳机动队</d>
<d p="1345.6690,4,25,14893055,1773934886,0,288811455,461">梦幻岛漫画后面也还行</d>
<d p="1350.8500,4,25,16772431,1773934890,0,6606769,462">确实</d>
<d p="1355.8930,4,25,14893055,1773934896,0,604035304,463">已经忘记梦幻岛剧情了</d>
<d p="1355.8930,4,25,14893055,1773934896,0,227618,464">那奇巧出租车可以再看</d>
<d p="1358.4760,4,25,14893055,1773934899,0,1604425,465">86动画也就那样吧</d>
<d p="1359.9580,4,25,16772431,1773934900,0,6606769,466">86有点慢热，我都没静下心去看</d>
<d p="1359.9580,4,25,14893055,1773934900,0,266375,467">确实</d>
<d p="1361.2500,1,25,16777215,1773934901,0,3427592,468">奇巧计程车的编剧本来是写电视剧的，所以味道不一样</d>
<d p="1365.1560,1,25,14893055,1773934905,0,14279,469">演一个出租车司机</d>
<d p="1370.1700,4,25,14893055,1773934910,0,87078921,470">86我纯看女主去了</d>
<d p="1370.1700,4,25,14893055,1773934910,0,1604425,471">演的是男主有病</d>
<d p="1371.6560,4,25,14893055,1773934911,0,34531495,472">草</d>
<d p="1375.5500,4,25,14893055,1773934915,0,9669499,473">[岁己收藏集表情包_哈哈]</d>
<d p="1376.8500,1,25,14893055,1773934916,0,14279,474">海象出租车司机，遇到了JK啊，黑帮啊，什么的</d>
<d p="1379.2800,4,25,14893055,1773934919,0,13429933,475">[岁己收藏集表情包_哈哈]</d>
<d p="1379.4540,4,25,16772431,1773934919,0,6606769,476">懂你的</d>
<d p="1383.1770,4,25,14893055,1773934922,0,604035304,477">好多前期比较慢热</d>
<d p="1383.1770,4,25,14893055,1773934923,0,227618,478">86感觉动画其实比小说做的好</d>
<d p="1385.9520,4,25,14893055,1773934926,0,288811455,479">没有给到主播</d>
<d p="1387.2550,4,25,14893055,1773934926,0,1673559,480">直接骂 </d>
<d p="1388.5500,1,25,16777215,1773934929,0,3427592,481">小黑猫是凶手</d>
<d p="1392.4610,4,25,16772431,1773934933,0,6606769,482">hhhhhh</d>
<d p="1393.7530,4,25,14893055,1773934934,0,266375,483">还是石头门好看</d>
<d p="1394.8840,4,25,14893055,1773934935,0,227618,484">[岁己收藏集表情包_哈哈]</d>
<d p="1394.8840,4,25,14893055,1773934935,0,1604425,485">男主有病看人都是动物</d>
<d p="1397.6490,4,25,16772431,1773934938,0,6606769,486">支持直接骂</d>
<d p="1398.7710,4,25,14893055,1773934939,0,227618,487">点开就想起来了</d>
<d p="1398.9630,1,25,14893055,1773934938,0,14279,488">什么都记住了</d>
<d p="1398.9630,4,25,14893055,1773934939,0,34531495,489">只需要一个提醒</d>
<d p="1398.9630,4,25,14893055,1773934939,0,9669499,490">听到OP就想起来了</d>
<d p="1402.6710,4,25,14893055,1773934943,0,604035304,491">看一下就回忆起来了</d>
<d p="1416.9910,4,25,14893055,1773934956,0,604035304,492">还有什么</d>
<d p="1421.0540,1,25,16777215,1773934960,0,3427592,493">小岁就差个锚点了</d>
<d p="1422.3610,4,25,16772431,1773934962,0,6606769,494">一起看一个片段就能回忆起来了</d>
<d p="1424.9500,1,25,14893055,1773934964,0,14279,495">学问猫学问猫</d>
<d p="1426.0630,4,25,14893055,1773934966,0,1604425,496">你偷吃了好多高质量作品 我跟你说</d>
<d p="1426.2610,4,25,14893055,1773934967,0,34531495,497">情景喜剧</d>
<d p="1428.8580,1,25,16777215,1773934968,0,3427592,498">有记忆锚点就记得了</d>
<d p="1428.8580,4,25,16772431,1773934969,0,6606769,499">我也是，喜欢重温</d>
<d p="1435.3510,1,25,14893055,1773934975,0,14279,500">我看完鬼灭剧场版想重温鬼灭动画</d>
<d p="1437.7690,4,25,14893055,1773934977,0,604035304,501">剧情还记得也可以看呀</d>
<d p="1441.6680,4,25,14893055,1773934981,0,227618,502">[岁己收藏集表情包_哈哈]</d>
<d p="1448.3550,1,25,16777215,1773934988,0,3427592,503">无法预料的命运的舞台！</d>
<d p="1449.4830,4,25,14893055,1773934990,0,604035304,504">未知的舞台</d>
<d p="1450.9570,4,25,14893055,1773934991,0,13327599,505">第二次看感觉可以看到一些第一次看没注意到的细节吧</d>
<d p="1452.0830,1,25,16777215,1773934992,0,8481710,506">喜欢有那种惊喜新鲜感吗</d>
<d p="1452.0830,4,25,14893055,1773934993,0,13429933,507">[岁己收藏集表情包_哈哈]</d>
<d p="1453.3870,4,25,14893055,1773934993,0,1604425,508">岁己这个心态适合追原创</d>
<d p="1453.3870,1,25,16777215,1773934993,0,2225137,509">我经常会重温石头门</d>
<d p="1453.3870,4,25,14893055,1773934993,0,4184347,510">是的</d>
<d p="1458.5910,4,25,14893055,1773934998,0,227618,511">我想了想我会二刷的其实还是有的</d>
<d p="1458.7510,4,25,14893055,1773934998,0,34531495,512">理解</d>
<d p="1460.0640,4,25,16772431,1773935000,0,6606769,513">就是想看甜甜甜呀</d>
<d p="1463.7690,4,25,14893055,1773935003,0,227618,514">但是你不喜欢……</d>
<d p="1463.9540,1,25,14893055,1773935004,0,14279,515">还好吧，小岁看我喜欢的我就看小岁重新reaction一遍</d>
<d p="1466.3860,4,25,14893055,1773935007,0,604035304,516">可以看看之前漏掉的一些细节</d>
<d p="1471.5780,4,25,14893055,1773935011,0,1604425,517">末日后酒店你自己看完了吗</d>
<d p="1475.6650,4,25,14893055,1773935015,0,9669499,518">[岁己收藏集表情包_笑了]</d>
<d p="1479.5570,4,25,14893055,1773935019,0,34531495,519">懂你意思了</d>
<d p="1487.3540,4,25,14893055,1773935027,0,34531495,520">喜欢刺激的</d>
<d p="1488.6630,4,25,14893055,1773935028,0,13327599,521">我现在也看下去之前看过的作品</d>
<d p="1488.6630,4,25,14893055,1773935029,0,9669499,522">看瑞克和莫蒂 这个肯定七上八下</d>
<d p="1489.9590,4,25,16772431,1773935030,0,6606769,523">我猎人看了四五遍，每次都看得很爽</d>
<d p="1492.5500,4,25,14893055,1773935032,0,13327599,524">看不下去</d>
<d p="1493.6680,4,25,14893055,1773935033,0,604035304,525">第二次看的时候会发现很多之前没注意到的细节</d>
<d p="1494.9880,1,25,16772431,1773935035,0,257596619,526">比如纳斯达克</d>
<d p="1497.6000,4,25,14893055,1773935037,0,227618,527">末日后酒店我看着觉得太慢节奏了……</d>
<d p="1501.4730,4,25,14893055,1773935041,0,1604425,528">已经是去年最好的原创了</d>
<d p="1501.6540,4,25,14893055,1773935041,0,9669499,529">[岁己收藏集表情包_哈哈]</d>
<d p="1502.9530,4,25,16772431,1773935043,0,6606769,530">哈哈哈哈哈哈</d>
<d p="1506.6740,1,25,16777215,1773935046,0,339001,531">我晕</d>
<d p="1507.9850,4,25,14893055,1773935048,0,604035304,532">瑞克莫迪后面的不太好看了</d>
<d p="1508.1570,1,25,14893055,1773935049,0,14279,533">看低俗小说，我就知道文森会和女人跳舞，也很期待看呢。还有念圣经</d>
<d p="1510.7530,1,25,16777215,1773935051,0,3427592,534">少女歌剧看了吗</d>
<d p="1515.7920,4,25,14893055,1773935055,0,604035304,535">看到第七季就没看了</d>
<d p="1518.3800,4,25,14893055,1773935058,0,87078921,536">后面有点无聊了</d>
<d p="1518.5490,4,25,14893055,1773935058,0,9669499,537">换配音之后变得怪怪的</d>
<d p="1522.4540,4,25,14893055,1773935062,0,385663492,538">人类衰退之时 小岁看过么？</d>
<d p="1522.4540,4,25,16772431,1773935062,0,6606769,539">瑞克现在感觉有点一般，没之前爆了</d>
<d p="1530.2500,4,25,14893055,1773935070,0,13327599,540">无头我就因为慢节奏弃了</d>
<d p="1532.6720,1,25,16777215,1773935072,0,8481710,541">烧烤一下</d>
<d p="1532.6720,4,25,14893055,1773935073,0,227618,542">末日后酒店就不是打打杀杀【</d>
<d p="1535.2920,4,25,14893055,1773935074,0,604035304,543">要铺垫一下</d>
<d p="1539.3540,4,25,14893055,1773935078,0,34531495,544">挺多老的都有点平淡</d>
<d p="1541.7740,4,25,14893055,1773935081,0,1604425,545">本质公路片呢</d>
<d p="1543.2510,4,25,16772431,1773935084,0,6606769,546">瑞克的前编剧去漫威了，说起漫威，要不要</d>
<d p="1546.9670,1,25,16777215,1773935087,0,2225137,547">我们的天元突破宝宝。。</d>
<d p="1548.2950,4,25,14893055,1773935088,0,227618,548">唉 星际牛仔……</d>
<d p="1549.5780,4,25,14893055,1773935090,0,604035304,549">nyanyanya</d>
<d p="1549.7600,4,25,16772431,1773935090,0,6606769,550">oh no</d>
<d p="1550.8740,4,25,14893055,1773935090,0,13429933,551">；；</d>
<d p="1551.0550,4,25,14893055,1773935091,0,13327599,552">小岁看过冰菓吗</d>
<d p="1552.3600,1,25,14893055,1773935092,0,14279,553">小岁小岁你别走</d>
<d p="1552.3600,1,25,16777215,1773935092,0,454001293,554">别走好吗</d>
<d p="1553.6670,4,25,16772431,1773935093,0,6606769,555">舍不得你的说</d>
<d p="1554.7700,4,25,14893055,1773935095,0,227618,556">[岁己收藏集表情包_啊啊啊]</d>
<d p="1556.2500,4,25,14893055,1773935096,0,34531495,557">又怎么了</d>
<d p="1557.3690,4,25,14893055,1773935097,0,4184347,558">别走</d>
<d p="1557.5600,1,25,16777215,1773935098,0,3546796261378753,559">别走</d>
<d p="1558.6730,4,25,14893055,1773935099,0,604035304,560">那我们明天下午继续只狼？</d>
<d p="1558.6730,1,25,16777215,1773935099,0,339001,561">啾咪啾</d>
<d p="1558.8570,4,25,14893055,1773935099,0,288811455,562">主播这周什么时候放假来着</d>
<d p="1561.2730,4,25,14893055,1773935101,0,87078921,563">别走，再聊聊</d>
<d p="1561.2730,4,25,14893055,1773935101,0,13429933,564">又咋了</d>
<d p="1561.4630,4,25,16772431,1773935101,0,6606769,565">岁小妹别走；；</d>
<d p="1562.5790,4,25,14893055,1773935103,0,604035304,566">咋了咋了？</d>
<d p="1564.0650,4,25,14893055,1773935103,0,13327599,567">又在看纳斯达克吗</d>
<d p="1565.2020,4,25,14893055,1773935104,0,378855235,568">再一会</d>
<d p="1570.5580,4,25,14893055,1773935110,0,288811455,569">是周六还是周五</d>
<d p="1570.5580,1,25,14893055,1773935110,0,14279,570">小岁说到英雄王，我们不再看10分钟学问猫吗</d>
<d p="1571.8670,4,25,14893055,1773935111,0,22389880,571">唉，星际牛仔...</d>
<d p="1573.1560,4,25,14893055,1773935113,0,9669499,572">[岁己收藏集表情包_妈呀]</d>
<d p="1574.2860,1,25,16777215,1773935114,0,8481710,573">别走 岁小妹</d>
<d p="1574.2860,4,25,14893055,1773935115,0,604035304,574">在看股票吗</d>
<d p="1574.4580,4,25,14893055,1773935114,0,34531495,575">涨了还是跌了</d>
<d p="1577.0490,4,25,16772431,1773935117,0,6606769,576">[岁己收藏集表情包_啵啵]</d>
<d p="1580.7770,4,25,14893055,1773935120,0,13429933,577">咋了咋了</d>
<d p="1583.3660,4,25,14893055,1773935124,0,604035304,578">哦！</d>
<d p="1585.9680,4,25,14893055,1773935126,0,227618,579">[岁己收藏集表情包_哈哈]</d>
<d p="1586.1560,1,25,14893055,1773935126,0,14279,580">那不看了</d>
<d p="1589.8780,1,25,16777215,1773935130,0,339001,581">哈哈嗯</d>
<d p="1590.0510,4,25,14893055,1773935130,0,9669499,582">学问猫是什么</d>
<d p="1591.1860,4,25,14893055,1773935132,0,4184347,583">看看啊，为什么不看</d>
<d p="1591.3550,4,25,14893055,1773935131,0,34531495,584">小岁</d>
<d p="1593.7670,4,25,14893055,1773935134,0,227618,585">又咋了到底</d>
<d p="1595.0640,4,25,14893055,1773935134,0,604035304,586">咋了咋了刚刚</d>
<d p="1596.5640,4,25,14893055,1773935137,0,34531495,587">叫我干什么</d>
<d p="1597.6680,4,25,14893055,1773935138,0,227618,588">？</d>
<d p="1600.3000,4,25,14893055,1773935140,0,13429933,589">[岁己收藏集表情包_妈呀]</d>
<d p="1600.3000,1,25,16777215,1773935140,0,8481710,590">小岁你真可爱</d>
<d p="1603.0510,1,25,14893055,1773935143,0,14279,591">那你错失了一个大猫</d>
<d p="1604.1710,4,25,14893055,1773935144,0,604035304,592">啊？你是岁己你真好笑</d>
<d p="1605.5030,1,25,16777215,1773935145,0,339001,593">问号</d>
<d p="1605.6510,4,25,14893055,1773935146,0,22389880,594">[岁己收藏集表情包_妈呀]</d>
<d p="1606.9510,4,25,14893055,1773935147,0,34531495,595">chou和可爱是可以共存的吗</d>
<d p="1608.0680,4,25,14893055,1773935148,0,604035304,596">我洗完了！！</d>
<d p="1608.0680,1,25,16777215,1773935149,0,8481710,597">为什么突然夸我</d>
<d p="1609.4070,1,25,16777215,1773935150,0,20094643,598">又看美股了是吧</d>
<d p="1610.6760,4,25,14893055,1773935150,0,227618,599">我怎么感觉你在说平时不会说的话</d>
<d p="1610.8560,1,25,16777215,1773935151,0,437619659,600">问号</d>
<d p="1611.9840,1,25,16777215,1773935152,0,2225137,601">怎么可能</d>
<d p="1612.1570,4,25,14893055,1773935152,0,34531495,602">我今天才洗澡</d>
<d p="1613.2710,4,25,14893055,1773935153,0,87078921,603">？</d>
<d p="1613.2710,4,25,14893055,1773935153,0,604035304,604">你洗澡了吗你</d>
<d p="1613.2710,1,25,16772431,1773935154,0,257596619,605">[岁己收藏集表情包_那很好了]</d>
<d p="1618.6570,4,25,14893055,1773935158,0,7254,606">嗯嗯</d>
<d p="1619.9550,4,25,16772431,1773935160,0,6606769,607">看学问猫是科普吉尔伽美什的，看了fate的都说塑造的比fate里的好</d>
<d p="1619.9550,4,25,14893055,1773935160,0,288811455,608">我是小猫</d>
<d p="1622.3740,4,25,14893055,1773935162,0,87078921,609">昨天才洗的</d>
<d p="1622.3740,4,25,14893055,1773935162,0,604035304,610">说话前言不搭后语了</d>
<d p="1622.5520,1,25,14893055,1773935163,0,14279,611">晚安晚安</d>
<d p="1623.8550,4,25,14893055,1773935164,0,13327599,612">神人</d>
<d p="1624.9650,4,25,14893055,1773935165,0,13429933,613">不许走</d>
<d p="1626.3200,4,25,14893055,1773935166,0,604035304,614">不许走！！</d>
<d p="1626.3200,4,25,14893055,1773935167,0,227618,615">[岁己收藏集表情包_哈哈]</d>
<d p="1627.7560,4,25,14893055,1773935167,0,9669499,616">你走吧</d>
<d p="1629.0610,4,25,14893055,1773935169,0,34531495,617">舍不得舍不得</d>
<d p="1630.1770,4,25,14893055,1773935170,0,87078921,618">别走</d>
<d p="1631.6550,4,25,14893055,1773935172,0,13327599,619">那你去吧</d>
<d p="1632.7870,4,25,14893055,1773935172,0,604035304,620">你不许走！</d>
<d p="1632.7870,1,25,16777215,1773935172,0,8481710,621">不许走</d>
<d p="1632.9510,4,25,16772431,1773935172,0,6606769,622">好哦，走吧</d>
<d p="1634.2600,1,25,16777215,1773935174,0,437619659,623">晚安</d>
<d p="1634.2600,4,25,16772431,1773935174,0,6606769,624">睡个好觉哦</d>
<d p="1635.5710,4,25,14893055,1773935176,0,34531495,625">不要你离开</d>
<d p="1637.9800,4,25,14893055,1773935178,0,227618,626">[岁己收藏集表情包_啊啊啊]</d>
<d p="1639.2920,4,25,14893055,1773935179,0,4184347,627">别走，我们来找点话题</d>
<d p="1644.4920,1,25,16777215,1773935184,0,2225137,628">拜拜喵</d>
<d p="1645.7850,4,25,14893055,1773935186,0,227618,629">？</d>
<d p="1645.7850,4,25,14893055,1773935186,0,13429933,630">何意</d>
<d p="1647.2520,4,25,14893055,1773935187,0,34531495,631">我的背很宽</d>
<d p="1648.3730,1,25,16777215,1773935189,0,20094643,632">一几一几一几</d>
<d p="1649.8550,1,25,16777215,1773935189,0,3427592,633">别回头，我是岁己</d>
<d p="1649.8550,4,25,14893055,1773935190,0,288811455,634">主播你这周什么时候放假！</d>
<d p="1652.4530,4,25,14893055,1773935193,0,13327599,635">你要在我后面干嘛</d>
<d p="1653.5800,4,25,14893055,1773935193,0,378855235,636">不能再多待一会么</d>
<d p="1653.5800,4,25,14893055,1773935194,0,227618,637">你在我哪个身后？</d>
<d p="1655.0510,4,25,14893055,1773935194,0,89479870,638">已老实</d>
<d p="1656.1740,4,25,14893055,1773935196,0,604035304,639">你在我身后干嘛？</d>
<d p="1656.3570,4,25,16772431,1773935197,0,6606769,640">小岁别回头</d>
<d p="1660.2570,4,25,14893055,1773935200,0,266375,641">要晚安了吗小岁</d>
<d p="1663.9980,1,25,16777215,1773935204,0,8481710,642">🐽</d>
<d p="1664.1570,4,25,16772431,1773935204,0,6606769,643">小岁现在这样像底特律诶</d>
<d p="1666.7500,4,25,14893055,1773935206,0,34531495,644">你要干什么</d>
<d p="1667.8700,4,25,14893055,1773935207,0,227618,645">[岁己收藏集表情包_妈呀]</d>
<d p="1667.8720,4,25,14893055,1773935208,0,604035304,646">对了那个话题怎样了</d>
<d p="1668.0530,1,25,14893055,1773935207,0,14279,647">别提醒岁己，岁己就会永远直播下去</d>
<d p="1673.2520,1,25,16777215,1773935213,0,3427592,648">再见了，岁小妹</d>
<d p="1675.8520,4,25,14893055,1773935215,0,34531495,649">草</d>
<d p="1678.2750,1,25,16777215,1773935218,0,8481710,650">我命令你去掉</d>
<d p="1678.2760,4,25,14893055,1773935218,0,227618,651">[岁己收藏集表情包_哈哈]</d>
<d p="1678.4510,1,25,16777215,1773935218,0,3427592,652">再见了，岁大姐</d>
<d p="1679.7580,4,25,14893055,1773935219,0,9669499,653">有框</d>
<d p="1681.0580,4,25,14893055,1773935220,0,34531495,654">🐽</d>
<d p="1682.1780,4,25,14893055,1773935222,0,1604425,655">你别说你躲在这里蹭我 还挺有感觉的</d>
<d p="1682.1780,4,25,14893055,1773935222,0,13429933,656">[岁己收藏集表情包_哈哈]</d>
<d p="1682.1780,1,25,16777215,1773935222,0,339001,657">哈哈嗯</d>
<d p="1684.7660,4,25,14893055,1773935224,0,604035304,658">可恶</d>
<d p="1686.0730,4,25,14893055,1773935225,0,4184347,659">我们今年能不能上mixup</d>
<d p="1687.5550,4,25,16772431,1773935227,0,6606769,660">再脱出三个小岁的影子就是底特律的封面诶</d>
<d p="1689.9840,1,25,16777215,1773935229,0,2225137,661">晚安，金闪闪</d>
<d p="1692.5700,4,25,14893055,1773935232,0,604035304,662">➡️🐷</d>
<d p="1695.1690,4,25,14893055,1773935235,0,4184347,663">来点事业民卡组</d>
<d p="1703.1520,4,25,16772431,1773935243,0,6606769,664">晚安闪大哥</d>
<d p="1704.4690,4,25,14893055,1773935244,0,34531495,665">🐖👉</d>
<d p="1705.5730,4,25,14893055,1773935246,0,227618,666">[岁己收藏集表情包_啊啊啊]</d>
<d p="1708.1720,4,25,14893055,1773935248,0,604035304,667">不许走</d>
<d p="1708.3600,4,25,16772431,1773935248,0,6606769,668">走吧小岁；；</d>
<d p="1709.6530,4,25,14893055,1773935250,0,288811455,669">；；</d>
<d p="1710.8120,4,25,14893055,1773935251,0,227618,670">又来</d>
<d p="1710.9530,4,25,14893055,1773935251,0,13327599,671">你走吧</d>
<d p="1712.2580,1,25,16777215,1773935252,0,3427592,672">好了小饼饼们</d>
<d p="1713.3720,4,25,14893055,1773935253,0,87078921,673">别走</d>
<d p="1713.3720,4,25,14893055,1773935253,0,378855235,674">别走好吗</d>
<d p="1713.3720,4,25,14893055,1773935254,0,13429933,675">；；</d>
<d p="1717.2770,4,25,14893055,1773935257,0,227618,676">我没关系啊</d>
<d p="1717.4540,4,25,14893055,1773935257,0,9669499,677">支持</d>
<d p="1717.4540,4,25,16772431,1773935258,0,6606769,678">啊？？</d>
<d p="1718.7570,1,25,14893055,1773935259,0,14279,679">我在那</d>
<d p="1718.7570,4,25,14893055,1773935259,0,34531495,680">我还在就行</d>
<d p="1718.7570,4,25,14893055,1773935259,0,288811455,681">什么地方？</d>
<d p="1719.8830,4,25,14893055,1773935259,0,604035304,682">都没有用少御音直播</d>
<d p="1719.8830,4,25,14893055,1773935260,0,227618,683">在头顶吗？</d>
<d p="1719.8830,4,25,14893055,1773935260,0,1604425,684">可以啊</d>
<d p="1720.0670,4,25,16772431,1773935259,0,6606769,685">可以啊</d>
<d p="1720.0670,1,25,16777215,1773935259,0,454001293,686">哪里</d>
<d p="1721.1830,4,25,14893055,1773935261,0,4184347,687">可以啊</d>
<d p="1721.3510,4,25,14893055,1773935261,0,9669499,688">支持抱在怀里</d>
<d p="1722.6540,4,25,14893055,1773935262,0,13327599,689">可以</d>
<d p="1722.6540,1,25,16777215,1773935262,0,3427592,690">我能在那里吗</d>
<d p="1723.7830,1,25,16777215,1773935263,0,10808911,691">在哪</d>
<d p="1723.7830,4,25,14893055,1773935263,0,13429933,692">在哪</d>
<d p="1723.7830,1,25,16777215,1773935264,0,2225137,693">我可以接受在你的脚底</d>
<d p="1723.9530,4,25,14893055,1773935263,0,34531495,694">放哪准备</d>
<d p="1725.0730,1,25,16777215,1773935264,0,20094643,695">我要在哪里</d>
<d p="1725.0730,4,25,14893055,1773935265,0,87078921,696">可以的</d>
<d p="1725.2560,1,25,16777215,1773935265,0,3546796261378753,697">在哪？</d>
<d p="1725.2560,1,25,14893055,1773935265,0,14279,698">我在胸口抱着吗，那我觉得不错</d>
<d p="1725.2560,4,25,16772431,1773935265,0,6606769,699">在哪？你的心口上吗</d>
<d p="1726.3850,4,25,14893055,1773935266,0,604035304,700">我存在于哪里那得看</d>
<d p="1726.3850,1,25,16777215,1773935266,0,8481710,701">那我在哪</d>
<d p="1728.9720,4,25,14893055,1773935269,0,604035304,702">我在哪里啊</d>
<d p="1729.1690,1,25,16777215,1773935268,0,3427592,703">我要在那里</d>
<d p="1730.2900,4,25,14893055,1773935270,0,1604425,704">只要别给我优化了就行</d>
<d p="1730.2910,4,25,14893055,1773935270,0,227618,705">后脑勺？</d>
<d p="1730.4980,4,25,14893055,1773935270,0,266375,706">可以</d>
<d p="1730.4980,1,25,16772431,1773935270,0,52194,707">烧烤一下</d>
<d p="1730.4980,4,25,14893055,1773935271,0,1673559,708">变成一个挂饰也可以的</d>
<d p="1731.7590,1,25,14893055,1773935271,0,14279,709">网袜里</d>
<d p="1731.7590,4,25,14893055,1773935272,0,34531495,710">我在你的怀里对吧</d>
<d p="1731.7590,4,25,14893055,1773935272,0,13327599,711">能随意出现吗</d>
<d p="1734.1780,4,25,14893055,1773935273,0,604035304,712">胸口吗</d>
<d p="1734.1780,4,25,14893055,1773935274,0,13429933,713">头上</d>
<d p="1735.4760,4,25,14893055,1773935275,0,1604425,714">不会是腿环吧</d>
<d p="1738.0970,4,25,14893055,1773935277,0,4184347,715">变成手偶可以吗</d>
<d p="1738.0980,4,25,14893055,1773935278,0,3546865991682507,716">[岁己收藏集表情包_羞死人了]</d>
<d p="1738.0980,1,25,16777215,1773935278,0,2225137,717">我可以接受在你的脚底</d>
<d p="1738.2520,4,25,16772431,1773935278,0,6606769,718">这叫智取，宝贝儿</d>
<d p="1739.3750,4,25,14893055,1773935280,0,604035304,719">帽子上？</d>
<d p="1742.1560,4,25,16772431,1773935282,0,6606769,720">心上</d>
<d p="1743.2870,4,25,14893055,1773935283,0,227618,721">哦 印在衣服上？</d>
<d p="1744.7510,4,25,14893055,1773935285,0,288811455,722">猜个锤子，快说</d>
<d p="1747.1760,4,25,14893055,1773935287,0,604035304,723">那估计就是胸口附近吧</d>
<d p="1748.6550,4,25,14893055,1773935288,0,34531495,724">我要在你帽子上面</d>
<d p="1748.6550,4,25,16772431,1773935288,0,6606769,725">是在心口吗</d>
<d p="1749.9520,1,25,16777215,1773935289,0,3546796261378753,726">在大腿上可以接受</d>
<d p="1753.8610,1,25,14893055,1773935294,0,14279,727">扒在头上</d>
<d p="1755.1550,4,25,14893055,1773935294,0,288811455,728">我会动吗？</d>
<d p="1755.1550,4,25,14893055,1773935295,0,266375,729">能在头上吗 想踩头了</d>
<d p="1756.4580,4,25,16772431,1773935297,0,6606769,730">爱你在  心口 难开</d>
<d p="1758.8740,4,25,14893055,1773935298,0,227618,731">[岁己收藏集表情包_哈哈]</d>
<d p="1758.8740,1,25,16777215,1773935299,0,339001,732">啾咪啾</d>
<d p="1760.1750,4,25,14893055,1773935300,0,4184347,733">手偶吗</d>
<d p="1760.3520,4,25,14893055,1773935300,0,6027898,734">难道是胸前的口袋里！？</d>
<d p="1761.4970,4,25,14893055,1773935302,0,1604425,735">外套胸口的兜兜上</d>
<d p="1761.6540,1,25,16777215,1773935301,0,3427592,736">你知道我想在那里</d>
<d p="1761.6540,4,25,14893055,1773935302,0,34531495,737">印着的还会眨眼睛吗</d>
<d p="1762.7800,4,25,14893055,1773935303,0,227618,738">那我还能动吗</d>
<d p="1766.8520,4,25,14893055,1773935306,0,288811455,739">我还能动吗？</d>
<d p="1768.1510,4,25,16772431,1773935308,0,6606769,740">[岁己收藏集表情包_啵啵]</d>
<d p="1769.2930,4,25,14893055,1773935309,0,1604425,741">那我的眨眼还和你本人绑定吗</d>
<d p="1771.8690,4,25,14893055,1773935312,0,604035304,742">那我就不能动了</d>
<d p="1772.0590,1,25,14893055,1773935311,0,14279,743">[岁己收藏集表情包_啊啊啊]</d>
<d p="1773.3610,4,25,16772431,1773935313,0,6606769,744">那我岂不是只能晃动了</d>
<d p="1775.7860,1,25,16777215,1773935316,0,2225137,745">排除在眼睛里</d>
<d p="1775.9580,4,25,14893055,1773935316,0,34531495,746">我还能眨眼睛吗</d>
<d p="1777.2530,4,25,16772431,1773935317,0,6606769,747">在肚子上？</d>
<d p="1778.3730,1,25,16777215,1773935318,0,50710531,748">揉揉揉岁岁萝嗯哼哼～戳小脸hhh</d>
<d p="1778.3730,4,25,14893055,1773935319,0,604035304,749">不会是挂件吧变成</d>
<d p="1779.6740,4,25,14893055,1773935320,0,4184347,750">是不是类似你穿中山装然后我在胸前的袋子里</d>
<d p="1781.1560,4,25,14893055,1773935321,0,22389880,751">[岁己收藏集表情包_啵啵]</d>
<d p="1782.4640,4,25,14893055,1773935322,0,9669499,752">[岁己收藏集表情包_哈哈]</d>
<d p="1784.8840,4,25,14893055,1773935325,0,1604425,753">原来饼干岁似了</d>
<d p="1785.0510,4,25,14893055,1773935325,0,34531495,754">在你的</d>
<d p="1786.1970,4,25,14893055,1773935325,0,227618,755">那看样子是在胃袋上了</d>
<d p="1786.1970,4,25,14893055,1773935325,0,604035304,756">心里没</d>
<d p="1786.3510,4,25,14893055,1773935327,0,9669499,757">变成挂件了</d>
<d p="1790.0820,1,25,16777215,1773935330,0,8481710,758">在你的心里</d>
<d p="1791.3990,4,25,14893055,1773935331,0,1604425,759">心里面</d>
<d p="1791.5670,4,25,14893055,1773935331,0,34531495,760">我在你心里吗</d>
<d p="1793.9890,4,25,14893055,1773935334,0,604035304,761">是不是胸口的位置挨着心脏</d>
<d p="1795.4500,4,25,16772431,1773935335,0,6606769,762">啊？</d>
<d p="1796.7520,4,25,14893055,1773935336,0,288811455,763">背面说是</d>
<d p="1799.1830,4,25,14893055,1773935339,0,604035304,764">背面？</d>
<d p="1800.4710,4,25,14893055,1773935340,0,227618,765">背面难绷</d>
<d p="1800.4710,4,25,14893055,1773935341,0,378855235,766">背面吗</d>
<d p="1801.7710,4,25,14893055,1773935341,0,4184347,767">背面能看到个鬼</d>
<d p="1801.7710,4,25,14893055,1773935342,0,1604425,768">那不是没出现</d>
<d p="1801.9560,4,25,16772431,1773935342,0,6606769,769">背面，该怎么看到呢</d>
<d p="1801.9560,1,25,16777215,1773935342,0,3427592,770">还有背面</d>
<d p="1801.9560,4,25,14893055,1773935342,0,34531495,771">怎么到背面去了</d>
<d p="1803.0870,4,25,14893055,1773935342,0,13429933,772">？</d>
<d p="1803.0870,4,25,14893055,1773935343,0,227618,773">看不见我了是吧</d>
<d p="1803.2570,4,25,14893055,1773935343,0,13327599,774">那不是完全看不到了[捂脸]</d>
<d p="1805.6820,4,25,14893055,1773935345,0,87078921,775">那不是没有了</d>
<d p="1805.6820,4,25,14893055,1773935346,0,13429933,776">背面说是</d>
<d p="1808.2700,1,25,16777215,1773935348,0,10808911,777">？</d>
<d p="1812.1860,1,25,16777215,1773935352,0,8481710,778">饼干岁痛衣？</d>
<d p="1812.1860,4,25,14893055,1773935352,0,604035304,779">那不是就露不出来了</d>
<d p="1812.1870,4,25,14893055,1773935353,0,1604425,780">原来是给饼干岁优化了</d>
<d p="1812.3540,1,25,16777215,1773935352,0,3427592,781">岁神哪边是背面</d>
<d p="1813.6550,4,25,16772431,1773935354,0,6606769,782">那有点吓人了</d>
<d p="1815.0000,4,25,14893055,1773935354,0,7254,783">[岁己收藏集表情包_妈呀]</d>
<d p="1815.0000,1,25,16772431,1773935354,0,11308264,784">问号</d>
<d p="1815.0000,1,25,16777215,1773935355,0,454001293,785">那还看得到我吗</d>
<d p="1815.0000,4,25,14893055,1773935355,0,34531495,786">草</d>
<d p="1816.0720,4,25,14893055,1773935356,0,13429933,787">你说我似了得了</d>
<d p="1817.3740,4,25,14893055,1773935357,0,227618,788">特别大也是看不见了</d>
<d p="1820.1510,4,25,14893055,1773935360,0,9669499,789">？</d>
<d p="1822.5680,1,25,16777215,1773935363,0,2225137,790">？那同人怎么画？</d>
<d p="1823.8860,4,25,14893055,1773935363,0,604035304,791">那你衣服是棕色内衬吗好搞笑</d>
<d p="1827.7690,4,25,14893055,1773935368,0,227618,792">也只有背面满印了</d>
<d p="1829.0810,4,25,14893055,1773935369,0,4184347,793">问号</d>
<d p="1829.2570,4,25,16772431,1773935368,0,6606769,794">正面能看到吗</d>
<d p="1830.3850,1,25,16772431,1773935371,0,257596619,795">[岁己收藏集表情包_哈哈]</d>
<d p="1830.5620,4,25,14893055,1773935370,0,13327599,796">小岁不想看到我可以直说的[委屈]</d>
<d p="1830.5620,1,25,16777215,1773935371,0,3427592,797">你听过，侠客行的故事吗，，，</d>
<d p="1831.6950,1,25,16777215,1773935371,0,50710531,798">唔呐，什么脸呢咩？</d>
<d p="1831.6950,1,25,16777215,1773935371,0,8481710,799">饼干岁痛衣吗</d>
<d p="1834.2650,4,25,14893055,1773935374,0,4184347,800">那也不必这样吧</d>
<d p="1834.4670,4,25,14893055,1773935374,0,34531495,801">妈呀</d>
<d p="1835.5710,4,25,14893055,1773935375,0,13429933,802">[岁己收藏集表情包_哈哈]</d>
<d p="1839.6620,4,25,14893055,1773935379,0,34531495,803">我吃成🐖了我</d>
<d p="1840.9550,1,25,16777215,1773935380,0,3546796261378753,804">饼干碎痛衣？</d>
<d p="1842.0980,4,25,14893055,1773935382,0,604035304,805">里面全是棕色饼干？不就成了豹纹了</d>
<d p="1843.3760,4,25,14893055,1773935383,0,13429933,806">饼干岁惨遭优化</d>
<d p="1844.8540,4,25,14893055,1773935384,0,22389880,807">[岁己收藏集表情包_哈哈]</d>
<d p="1847.2760,4,25,14893055,1773935387,0,1604425,808">幽默</d>
<d p="1848.5780,4,25,14893055,1773935389,0,227618,809">太惨了 我</d>
<d p="1848.7560,4,25,14893055,1773935388,0,1673559,810">倒也不必</d>
<d p="1848.7560,1,25,14893055,1773935389,0,14279,811">晚安</d>
<d p="1851.3520,4,25,14893055,1773935391,0,34531495,812">你怎么这样</d>
<d p="1856.5520,4,25,14893055,1773935397,0,13327599,813">想岁了</d>
<d p="1857.6900,4,25,14893055,1773935397,0,604035304,814">不许走！！</d>
<d p="1860.2770,4,25,14893055,1773935400,0,227618,815">[岁己收藏集表情包_啊啊啊]</d>
<d p="1861.5930,4,25,14893055,1773935401,0,87078921,816">不要走</d>
<d p="1861.7550,1,25,16777215,1773935402,0,3427592,817">再见了，岁大哥，岁小弟，岁大姐，岁小妹</d>
<d p="1863.0540,4,25,14893055,1773935403,0,22389880,818">小岁小岁！</d>
<d p="1865.6520,4,25,14893055,1773935405,0,34531495,819">舍不得</d>
<d p="1868.0780,4,25,14893055,1773935408,0,604035304,820">还没满足不许走</d>
<d p="1871.9810,4,25,14893055,1773935412,0,13429933,821">还真是</d>
<d p="1874.7560,4,25,16772431,1773935415,0,6606769,822">听着像jojo4里的替身，附着在小岁的背上</d>
<d p="1874.7560,4,25,14893055,1773935415,0,34531495,823">不要你离开</d>
<d p="1877.1870,4,25,14893055,1773935417,0,4184347,824">问号</d>
<d p="1878.4840,4,25,14893055,1773935418,0,604035304,825">啊啊啊啊舍不得啊</d>
<d p="1878.6520,4,25,14893055,1773935418,0,13327599,826">去吧</d>
<d p="1879.7990,1,25,16777215,1773935420,0,339001,827">啾咪啾</d>
<d p="1879.7990,1,25,16777215,1773935420,0,8481710,828">别走</d>
<d p="1882.3890,1,25,16777215,1773935422,0,2225137,829">再见👋，闪大哥</d>
<d p="1885.1580,4,25,16772431,1773935426,0,6606769,830">宋娜，我还没爽呢</d>
<d p="1886.2710,4,25,14893055,1773935426,0,13429933,831">晚安</d>
<d p="1887.7600,4,25,14893055,1773935427,0,22389880,832">已老实</d>
<d p="1887.7600,4,25,14893055,1773935428,0,266375,833">拜拜；；</d>
<d p="1891.4920,4,25,14893055,1773935431,0,378855235,834">好吧拜拜</d>
<d p="1894.0720,1,25,16777215,1773935434,0,8481710,835">欧漏</d>
<d p="1899.3050,1,25,16777215,1773935439,0,50710531,836">安安啦梦咩，岁岁萝扑倒～</d>
<d p="1899.4640,4,25,14893055,1773935440,0,34531495,837">[岁己收藏集表情包_晚安]</d>
<d p="1899.4640,4,25,14893055,1773935440,0,266375,838">晚安小岁</d>
<d p="1902.0520,4,25,14893055,1773935442,0,266375,839">晚安</d>
<d p="1909.8660,4,25,14893055,1773935450,0,34531495,840">小岁小岁</d>
<d p="1909.8660,4,25,14893055,1773935450,0,1673559,841">好像观众签到 主播还能领金仓鼠 家人们签下到</d>
<d p="1910.9980,1,25,16777215,1773935451,0,8481710,842">小岁啊！</d>
<d p="1912.2980,4,25,14893055,1773935452,0,227618,843">[岁己收藏集表情包_啊啊啊]</d>
<d p="1913.5720,4,25,14893055,1773935453,0,13429933,844">小岁啊</d>
<d p="1916.3560,4,25,16772431,1773935457,0,6606769,845">小岁子牙</d>
<d p="1917.4780,4,25,14893055,1773935457,0,13429933,846">[岁己收藏集表情包_啊啊啊]</d>
<d p="1918.9660,4,25,16772431,1773935459,0,6606769,847">[岁己收藏集表情包_啵啵]</d>
<d p="1920.0840,4,25,14893055,1773935460,0,227618,848">又怎么了</d>
<d p="1921.3750,4,25,14893055,1773935461,0,604035304,849">岁子宝啊</d>
<d p="1921.5620,1,25,16777215,1773935461,0,3546796261378753,850">小岁～</d>
<d p="1922.8530,4,25,14893055,1773935462,0,22389880,851">小岁...</d>
<d p="1924.1540,4,25,14893055,1773935465,0,258865753,852">晚安小岁</d>
<d p="1924.1540,4,25,14893055,1773935465,0,13327599,853">干嘛</d>
<d p="1926.5810,4,25,14893055,1773935466,0,4184347,854">干嘛</d>
<d p="1926.5810,1,25,16777215,1773935467,0,8481710,855">岁子啊岁</d>
<d p="1926.7530,4,25,14893055,1773935466,0,34531495,856">想你</d>
<d p="1931.7740,4,25,14893055,1773935471,0,378855235,857">在呢在呢</d>
<d p="1931.9660,4,25,14893055,1773935471,0,1673559,858">怎么了怎么了</d>
<d p="1933.0710,4,25,14893055,1773935473,0,604035304,859">岁子包啊</d>
<d p="1933.2520,4,25,14893055,1773935473,0,6027898,860">小岁啊小岁；；</d>
<d p="1940.8850,4,25,14893055,1773935481,0,4184347,861">想我怎么不多播一会</d>
<d p="1942.1910,1,25,16777215,1773935482,0,339001,862">啾咪啾</d>
<d p="1942.3520,4,25,16772431,1773935482,0,6606769,863">[岁己收藏集表情包_啵啵]</d>
<d p="1943.4750,4,25,14893055,1773935483,0,604035304,864">咋了咋了有心事吗</d>
<d p="1944.7810,1,25,16777215,1773935485,0,2225137,865">没几天就要四月份了，这时间快的好讨厌啊</d>
<d p="1944.7810,1,25,16777215,1773935485,0,8481710,866">小朋友你是有很多烦恼</d>
<d p="1946.0780,4,25,14893055,1773935485,0,227618,867">你说话啊</d>
<d p="1947.5630,4,25,16772431,1773935488,0,6606769,868">小岁子牙</d>
<d p="1948.8550,4,25,14893055,1773935489,0,258865753,869">小岁小岁</d>
<d p="1951.4530,4,25,14893055,1773935491,0,13327599,870">我以为我们一直有话说</d>
<d p="1952.5750,4,25,14893055,1773935493,0,13429933,871">小岁小岁</d>
<d p="1953.8700,4,25,14893055,1773935494,0,604035304,872">岁岁！</d>
<d p="1954.0610,4,25,14893055,1773935493,0,34531495,873">你是否有很多问好</d>
<d p="1955.3540,4,25,14893055,1773935495,0,9669499,874">其实是玩手机去了</d>
<d p="1959.0740,1,25,16777215,1773935499,0,8481710,875">小岁小岁！</d>
<d p="1961.6710,4,25,14893055,1773935501,0,87078921,876">小岁小岁</d>
<d p="1962.9780,4,25,14893055,1773935503,0,604035304,877">你还在吗</d>
<d p="1964.2730,1,25,16777215,1773935504,0,8481710,878">为何叹气</d>
<d p="1969.4830,4,25,14893055,1773935509,0,604035304,879">舍不得啊</d>
<d p="1970.9540,4,25,14893055,1773935510,0,22389880,880">怎么了小岁</d>
<d p="1974.8560,4,25,14893055,1773935514,0,6027898,881">怎么了小岁</d>
<d p="1974.8560,1,25,16777215,1773935515,0,2391266,882">晚安</d>
<d p="1976.1540,4,25,14893055,1773935516,0,34531495,883">你是</d>
<d p="1978.5680,1,25,16777215,1773935519,0,2225137,884">再见了妈妈今晚我就要远航</d>
<d p="1981.3520,1,25,16772431,1773935521,0,52194,885">合股叹气</d>
<d p="1983.9590,1,25,14893055,1773935523,0,14279,886">好了</d>
<d p="1983.9590,4,25,14893055,1773935524,0,9669499,887">看情况</d>
<d p="1985.0760,4,25,14893055,1773935524,0,227618,888">有的。</d>
<d p="1985.2540,4,25,14893055,1773935525,0,22389880,889">想岁了</d>
<d p="1986.5660,4,25,16772431,1773935526,0,6606769,890">有的</d>
<d p="1986.5660,1,25,14893055,1773935527,0,14279,891">[岁己收藏集表情包_好耶]</d>
<d p="1987.6820,4,25,14893055,1773935527,0,604035304,892">有啊</d>
<d p="1987.6820,4,25,14893055,1773935527,0,87078921,893">有的</d>
<d p="1987.6820,4,25,14893055,1773935528,0,4184347,894">看你播什么了</d>
<d p="1988.9930,1,25,16777215,1773935529,0,10808911,895">有的有的</d>
<d p="1988.9930,4,25,14893055,1773935529,0,13429933,896">好了</d>
<d p="1989.1550,1,25,16772431,1773935528,0,52194,897">有啊</d>
<d p="1989.1550,4,25,14893055,1773935529,0,13327599,898">看情况</d>
<d p="1990.4580,4,25,14893055,1773935530,0,34531495,899">很多时候都是有的吧</d>
<d p="1990.4580,4,25,14893055,1773935530,0,288811455,900">看情况</d>
<d p="1990.4580,4,25,16772431,1773935530,0,6606769,901">[岁己收藏集表情包_啵啵]</d>
<d p="1991.5790,1,25,16777215,1773935531,0,8481710,902">听到小岁的声音就开心了</d>
<d p="1991.7700,4,25,14893055,1773935531,0,266375,903">有啊 当然有啊</d>
<d p="1991.7710,4,25,14893055,1773935532,0,22389880,904">有的哦小岁</d>
<d p="1992.8660,1,25,16777215,1773935533,0,2225137,905">看直播内容</d>
<d p="1994.3530,4,25,14893055,1773935533,0,258865753,906">有的</d>
<d p="1995.4720,4,25,14893055,1773935536,0,378855235,907">当然了</d>
<d p="1995.6520,4,25,14893055,1773935535,0,7254,908">我是卡皮巴拉 </d>
<d p="1998.0740,4,25,14893055,1773935538,0,604035304,909">我有的，但是我不满足</d>
<d p="1999.5540,4,25,14893055,1773935539,0,34531495,910">有的</d>
<d p="2002.1510,4,25,14893055,1773935542,0,34531495,911">今天很有的</d>
<d p="2004.5790,4,25,14893055,1773935545,0,1604425,912">如果说有 你会收获到成就感吗</d>
<d p="2005.8930,4,25,14893055,1773935546,0,13429933,913">有的</d>
<d p="2006.0600,4,25,14893055,1773935545,0,1673559,914">有的说！</d>
<d p="2006.0600,4,25,16772431,1773935545,0,6606769,915">看直播的时候忘却了很多的烦恼，非常的开心</d>
<d p="2008.4760,4,25,14893055,1773935548,0,604035304,916">有啊</d>
<d p="2008.4760,4,25,14893055,1773935549,0,4184347,917">今天就那样吧</d>
<d p="2008.6520,4,25,16772431,1773935548,0,6606769,918">有的</d>
<d p="2013.6790,4,25,14893055,1773935553,0,227618,919">今天有的</d>
<d p="2013.8550,4,25,14893055,1773935553,0,13327599,920">还好</d>
<d p="2013.8550,4,25,14893055,1773935553,0,9669499,921">不排除看完直播被气晕的情况</d>
<d p="2015.1540,4,25,14893055,1773935555,0,288811455,922">您这个问题我暂时没法回答，你过会再来问吧</d>
<d p="2016.2990,4,25,14893055,1773935556,0,604035304,923">当然有了</d>
<d p="2017.5760,1,25,16777215,1773935558,0,505565330,924">今天的说</d>
<d p="2017.7560,4,25,14893055,1773935557,0,6027898,925">会怅然若失你信吗</d>
<d p="2017.7560,4,25,14893055,1773935558,0,9669499,926">[岁己收藏集表情包_笑了]</d>
<d p="2019.0550,4,25,14893055,1773935558,0,266375,927">[岁己收藏集表情包_啵啵]</d>
<d p="2024.2580,1,25,14893055,1773935564,0,14279,928">[岁己收藏集表情包_啵啵]</d>
<d p="2026.8530,4,25,16772431,1773935566,0,6606769,929">非常的开心，我每天就指望着小岁的直播活呢</d>
<d p="2028.1570,4,25,14893055,1773935568,0,34531495,930">当然一直都是有意义的</d>
<d p="2028.1570,1,25,14893055,1773935568,0,14279,931">小岁小岁</d>
<d p="2031.8860,4,25,14893055,1773935571,0,1604425,932">那就多肯定肯定你吧</d>
<d p="2031.8860,1,25,16777215,1773935572,0,8481710,933">听到小岁的声音就感觉好治愈</d>
<d p="2032.0570,4,25,16772431,1773935572,0,6606769,934">小岁就是我的充电宝</d>
<d p="2035.9550,4,25,14893055,1773935576,0,1673559,935">[岁己收藏集表情包_哭死]</d>
<d p="2035.9550,4,25,16772431,1773935576,0,6606769,936">[岁己收藏集表情包_啵啵]</d>
<d p="2038.3800,4,25,14893055,1773935578,0,604035304,937">会还想要更多</d>
<d p="2046.3660,4,25,14893055,1773935586,0,9669499,938">[岁己收藏集表情包_羞死人了]</d>
<d p="2048.9580,4,25,14893055,1773935588,0,12052692,939">宝宝你快回来，你还能更有意义一点 我刚要下班！</d>
<d p="2050.0740,4,25,14893055,1773935590,0,13429933,940">[岁己收藏集表情包_啵啵]</d>
<d p="2051.5570,4,25,16772431,1773935592,0,6606769,941">有被小岁治愈到！</d>
<d p="2052.8550,4,25,14893055,1773935593,0,34531495,942">每一天都是我们很珍贵的记忆</d>
<d p="2055.4650,4,25,14893055,1773935595,0,22389880,943">跳恰恰</d>
<d p="2055.4650,4,25,16772431,1773935595,0,6606769,944">[岁己收藏集表情包_啵啵]</d>
<d p="2060.4860,1,25,16777215,1773935600,0,8481710,945">[岁己收藏集表情包_啵啵]</d>
<d p="2064.5530,4,25,14893055,1773935604,0,6027898,946">明天还能见面就好；；</d>
<d p="2081.2710,1,25,16777215,1773935621,0,8481710,947">小岁小岁</d>
<d p="2091.6730,4,25,14893055,1773935632,0,604035304,948">舍不得的说</d>
<d p="2093.1560,4,25,14893055,1773935632,0,1673559,949"> 岁宝岁宝</d>
<d p="2093.1560,1,25,16772431,1773935633,0,1387696,950">啾咪啾</d>
<d p="2099.6620,1,25,16772431,1773935639,0,11308264,951">[岁己收藏集表情包_晚安]</d>
<d p="2099.6620,4,25,14893055,1773935640,0,34531495,952">[岁己收藏集表情包_晚安]</d>
<d p="2103.5590,4,25,14893055,1773935643,0,6027898,953">小岁小岁~</d>
<d p="2104.8530,4,25,16772431,1773935645,0,6606769,954">[岁己收藏集表情包_啵啵]</d>
<d p="2113.7770,4,25,14893055,1773935654,0,604035304,955">还没到 12 点呢</d>
<d p="2121.5830,1,25,16777215,1773935661,0,2225137,956">内服药</d>
<d p="2125.4760,4,25,14893055,1773935666,0,4184347,957">已老实</d>
<d p="2125.6610,4,25,14893055,1773935665,0,22389880,958">别走好吗</d>
<d p="2139.7700,4,25,14893055,1773935680,0,13429933,959">晚安</d>
<d p="2142.3790,1,25,16777215,1773935682,0,8481710,960">晚安</d>
<d p="2149.0600,4,25,16772431,1773935688,0,6606769,961">[岁己收藏集表情包_啵啵]</d>
<d p="2152.9560,4,25,14893055,1773935693,0,13327599,962">嗨呀，这个BGM又是果/体圆舞曲</d>
<d p="2152.9560,4,25,14893055,1773935693,0,6027898,963">[岁己收藏集表情包_啵啵]</d>
<d p="2155.5550,4,25,16772431,1773935696,0,6606769,964">晚安的说哦</d>
<d p="2160.5810,1,25,16777215,1773935700,0,10808911,965">晚安</d>
<d p="2163.1780,4,25,14893055,1773935703,0,13429933,966">晚安</d>
<d p="2164.4810,1,25,16777215,1773935705,0,2225137,967">妈呀这个雨中月在说什么呢</d>
<d p="2167.2560,4,25,14893055,1773935706,0,13327599,968">晚安</d>
<d p="2167.2560,4,25,16772431,1773935707,0,6606769,969">希望小岁也能获取到能量呢</d>
<d p="2169.8580,4,25,14893055,1773935710,0,9669499,970">[岁己收藏集表情包_流汗了]</d>
<d p="2171.1540,4,25,16772431,1773935710,0,6606769,971">[岁己收藏集表情包_啵啵]</d>
<d p="2175.0540,4,25,14893055,1773935715,0,14910777,972">晚安</d>
<d p="2178.7780,4,25,14893055,1773935718,0,13429933,973">晚安</d>
<d p="2188.0580,4,25,14893055,1773935727,0,13327599,974">喜欢这首</d>
<d p="2190.6580,4,25,14893055,1773935731,0,22389880,975">小岁小岁，是不是在偷跑了</d>
<d p="2204.7700,4,25,14893055,1773935744,0,4184347,976">已老实</d>
<d p="2223.1520,4,25,14893055,1773935763,0,6027898,977">小岁…</d>
<d p="2224.2820,4,25,14893055,1773935763,0,13429933,978">薛定谔的鞋码</d>
<d p="2242.4830,4,25,14893055,1773935782,0,227618,979">还没洗……要去洗的</d>
<d p="2258.0930,1,25,16777215,1773935798,0,8481710,980">我是毒液我是毒液</d>
<d p="2260.8640,4,25,14893055,1773935800,0,22389880,981">啾咪啾</d>
<d p="2267.3600,4,25,14893055,1773935807,0,288811455,982">你不是姐</d>
<d p="2268.4770,4,25,14893055,1773935809,0,4184347,983">解了什么</d>
<d p="2269.7820,4,25,14893055,1773935809,0,604035304,984">花的告白礼物怎么没了....</d>
<d p="2269.9600,4,25,14893055,1773935810,0,34531495,985">[岁己收藏集表情包_晚安]</d>
<d p="2272.5590,4,25,16772431,1773935812,0,6606769,986">[岁己收藏集表情包_啵啵]</d>
<d p="2281.4710,1,25,16777215,1773935821,0,2225137,987">咖啡</d>
<d p="2282.9530,4,25,14893055,1773935822,0,288811455,988">卡，飞</d>
<d p="2286.6850,4,25,14893055,1773935826,0,13429933,989">[岁己收藏集表情包_好听]</d>
<d p="2290.7600,4,25,14893055,1773935830,0,13327599,990">哔哩哔哩删了好多礼物</d>
<d p="2291.8750,4,25,14893055,1773935831,0,4184347,991">继续唱</d>
<d p="2292.0550,4,25,16772431,1773935831,0,6606769,992">[岁己收藏集表情包_啵啵]</d>
<d p="2297.0890,4,25,14893055,1773935837,0,604035304,993">收藏在哪里</d>
<d p="2299.8540,4,25,16772431,1773935840,0,6606769,994">拜比拜比</d>
<d p="2305.0600,4,25,16772431,1773935845,0,6606769,995">支持告白气球</d>
<d p="2306.3540,1,25,16777215,1773935846,0,393237576,996">晚安晚安</d>
<d p="2310.0750,1,25,16777215,1773935849,0,2225137,997">晚安</d>
<d p="2311.5530,4,25,14893055,1773935852,0,34531495,998">[岁己收藏集表情包_啵啵]</d>
<d p="2313.9830,1,25,16777215,1773935853,0,8481710,999">晚安</d>
<d p="2315.2890,1,25,16772431,1773935856,0,257596619,1000">晚安</d>
<d p="2316.7650,4,25,14893055,1773935856,0,13327599,1001">晚安</d>
<d p="2318.0550,4,25,14893055,1773935857,0,34531495,1002">好哦</d>
<d p="2320.6580,4,25,14893055,1773935860,0,9669499,1003">晚安</d>
<d p="2325.8610,4,25,14893055,1773935865,0,258865753,1004">晚安</d>
<d p="2326.9880,4,25,14893055,1773935866,0,227618,1005">晚安。拜拜。明天见。</d>
<d p="2328.4540,4,25,14893055,1773935868,0,34531495,1006">晚安哦</d>
<d p="2329.5870,4,25,14893055,1773935869,0,4184347,1007">主播主播想问一下五一的时候活动是几点开始</d>
<d p="2336.2560,4,25,16772431,1773935876,0,6606769,1008">[岁己收藏集表情包_啵啵]</d>
<d p="2338.6730,4,25,14893055,1773935879,0,4184347,1009">早上是不是很早来着</d>
<d p="2346.6530,4,25,16772431,1773935887,0,6606769,1010">man</d>
<d p="2350.3750,4,25,14893055,1773935890,0,4184347,1011">我去，飞机</d>
<d p="2350.5540,4,25,14893055,1773935891,0,34531495,1012">不会的</d>
<d p="2354.4560,4,25,14893055,1773935894,0,288811455,1013">主播；；你会出现吗；；</d>
<d p="2356.8750,4,25,14893055,1773935896,0,604035304,1014">看不腻的 明天下午我来不了应该...</d>
<d p="2356.8750,4,25,14893055,1773935897,0,13429933,1015">我去，飞机</d>
<d p="2358.1910,1,25,16777215,1773935897,0,339001,1016">啾咪啾</d>
<d p="2362.2580,4,25,14893055,1773935902,0,9669499,1017">？</d>
<d p="2362.2580,4,25,14893055,1773935902,0,34531495,1018">还有这么不环保的礼物</d>
<d p="2364.6790,4,25,14893055,1773935904,0,227618,1019">[岁己收藏集表情包_妈呀]</d>
<d p="2366.1560,4,25,14893055,1773935906,0,9669499,1020">怎么坠机了</d>
<d p="2367.2860,4,25,14893055,1773935907,0,13429933,1021">man</d>
<d p="2367.4800,4,25,14893055,1773935907,0,22389880,1022">[岁己收藏集表情包_流汗了]</d>
<d p="2367.4800,4,25,16772431,1773935908,0,6606769,1023">[岁己收藏集表情包_哈哈]</d>
<d p="2367.4800,4,25,14893055,1773935908,0,288811455,1024">主播你还会出现吗；；</d>
<d p="2369.8730,4,25,14893055,1773935909,0,378855235,1025">哈哈哈</d>
<d p="2372.4870,1,25,16777215,1773935912,0,2225137,1026">mayday mayday</d>
<d p="2372.6620,4,25,14893055,1773935913,0,6027898,1027">怎么坠机了</d>
<d p="2376.5520,4,25,14893055,1773935916,0,258865753,1028">man</d>
<d p="2377.6930,4,25,14893055,1773935917,0,4184347,1029">点歌 see you again</d>
<d p="2379.1620,4,25,16772431,1773935919,0,6606769,1030">飞伊朗的？</d>
<d p="2379.1620,4,25,14893055,1773935920,0,34531495,1031">别坠机</d>
<d p="2381.5780,1,25,16777215,1773935922,0,8481710,1032">man！</d>
<d p="2382.8890,4,25,14893055,1773935922,0,604035304,1033">飞机怎么和超跑一个价格</d>
<d p="2384.3570,4,25,14893055,1773935923,0,22389880,1034">man！</d>
<d p="2384.3570,4,25,16772431,1773935924,0,6606769,1035">点歌 see you again</d>
<d p="2385.5000,4,25,14893055,1773935926,0,227618,1036">真要挂Mayday了</d>
<d p="2390.6990,4,25,14893055,1773935930,0,13429933,1037">man！</d>
<d p="2392.1680,4,25,14893055,1773935932,0,13327599,1038">牢岁</d>
<d p="2392.1680,4,25,14893055,1773935932,0,34531495,1039">草</d>
<d p="2395.8800,4,25,14893055,1773935936,0,227618,1040">[岁己收藏集表情包_哈哈]</d>
<d p="2399.9550,4,25,16772431,1773935940,0,6606769,1041">[岁己收藏集表情包_哈哈]</d>
<d p="2401.0960,4,25,14893055,1773935941,0,227618,1042">你下播再关呀</d>
<d p="2402.5570,4,25,14893055,1773935942,0,288811455,1043">真素的</d>
<d p="2403.6830,4,25,14893055,1773935944,0,604035304,1044">下播了再关吧</d>
<d p="2404.9740,1,25,16777215,1773935945,0,457710127,1045">-50</d>
<d p="2406.4600,4,25,16772431,1773935946,0,6606769,1046">怎么了啦</d>
<d p="2410.1820,4,25,14893055,1773935949,0,4184347,1047">主播已经收够米了，暗示大家别打了</d>
<d p="2410.3600,4,25,16772431,1773935950,0,6606769,1048">[岁己收藏集表情包_啵啵]</d>
<d p="2415.3800,4,25,14893055,1773935955,0,227618,1049">[岁己收藏集表情包_哈哈]</d>
<d p="2419.2850,4,25,14893055,1773935959,0,13429933,1050">[岁己收藏集表情包_哈哈]</d>
<d p="2419.4520,4,25,14893055,1773935959,0,9669499,1051">以为</d>
<d p="2422.0540,4,25,14893055,1773935962,0,288811455,1052">我帮你</d>
<d p="2423.3580,4,25,14893055,1773935963,0,288811455,1053">小岁姐姐我最近快累到虚脱了特别累的时候真的好想躺在大姐姐的腿上打盹呀（好像有点不</d>
<d p="2424.6610,4,25,14893055,1773935965,0,34531495,1054">bgs都是很man的人</d>
<d p="2433.5990,4,25,14893055,1773935973,0,227618,1055">[岁己收藏集表情包_妈呀]</d>
<d p="2433.5990,4,25,14893055,1773935974,0,604035304,1056">正好可以少御音了</d>
<d p="2433.7550,4,25,14893055,1773935974,0,9669499,1057">[诺比小兔_PNG_沉默]</d>
<d p="2438.7860,1,25,16777215,1773935978,0,8481710,1058">晚安</d>
<d p="2441.3950,4,25,14893055,1773935982,0,1604425,1059">岁己平时下播很久都不关obs的 会偷偷窥视饼干岁发什么弹幕</d>
<d p="2447.8770,4,25,14893055,1773935987,0,227618,1060">他的重点根本不是累吧</d>
<d p="2454.3890,1,25,16777215,1773935994,0,2225137,1061">晚安</d>
<d p="2457.1560,4,25,14893055,1773935997,0,1673559,1062">他想躺你腿上了 这个维斯</d>
<d p="2458.4610,4,25,14893055,1773935998,0,288811455,1063">卧槽</d>
<d p="2459.5980,4,25,14893055,1773935999,0,378855235,1064">哇</d>
<d p="2459.7610,1,25,14893055,1773936000,0,14279,1065">哇哇哇跨日了</d>
<d p="2462.3640,4,25,14893055,1773936002,0,22389880,1066">哇哇哇我要躺</d>
<d p="2462.3640,4,25,14893055,1773936002,0,13327599,1067">哇哇哇，跨日快乐[哇]</d>
<d p="2466.0800,4,25,14893055,1773936005,0,604035304,1068">我也想躺</d>
<d p="2466.0800,4,25,14893055,1773936006,0,13429933,1069">哇哇哇跨日快乐</d>
<d p="2466.2680,4,25,14893055,1773936005,0,12052692,1070">[暹罗厘普收藏集_亲亲]</d>
<d p="2467.3850,4,25,14893055,1773936007,0,4184347,1071">支持躺腿</d>
<d p="2467.3850,4,25,14893055,1773936007,0,227618,1072">跨日快乐</d>
<d p="2468.7110,4,25,14893055,1773936008,0,87078921,1073">跨日快乐</d>
<d p="2471.2740,4,25,14893055,1773936011,0,604035304,1074">跨日了啊啊啊</d>
<d p="2471.4540,4,25,14893055,1773936011,0,9669499,1075">大姐姐[爱]</d>
<d p="2472.7570,4,25,14893055,1773936012,0,34531495,1076">跨日快乐</d>
<d p="2472.7570,4,25,14893055,1773936012,0,258865753,1077">跨日快乐</d>
<d p="2474.0630,1,25,16772431,1773936014,0,1387696,1078">哇哇哇跨日了</d>
<d p="2475.1710,1,25,16777215,1773936015,0,2225137,1079">大姐姐你腿硌到我了</d>
<d p="2476.5070,4,25,14893055,1773936016,0,378855235,1080">跨日快乐</d>
<d p="2479.2500,4,25,14893055,1773936018,0,22389880,1081">哇哇哇跨日快乐！</d>
<d p="2481.6780,4,25,14893055,1773936022,0,227618,1082">[岁己收藏集表情包_妈呀]</d>
<d p="2481.6780,4,25,14893055,1773936022,0,4184347,1083">气节吗</d>
<d p="2481.8550,4,25,14893055,1773936022,0,12052692,1084">哇哇跨日了</d>
<d p="2481.8550,4,25,16772431,1773936022,0,6606769,1085">弥（月）（点）酥（岁）己的意思？</d>
<d p="2485.7490,4,25,14893055,1773936025,0,34531495,1086">人有点多</d>
<d p="2485.7490,4,25,14893055,1773936026,0,12052692,1087">哈哈哈</d>
<d p="2487.0570,4,25,14893055,1773936026,0,9669499,1088">[岁己收藏集表情包_哈哈]</d>
<d p="2489.6460,4,25,14893055,1773936029,0,288811455,1089">啧啧</d>
<d p="2492.2470,4,25,14893055,1773936033,0,13327599,1090">米酥己</d>
<d p="2494.8420,4,25,16772431,1773936034,0,6606769,1091">哇哇哇，跨日快乐的说！</d>
<d p="2497.2790,4,25,14893055,1773936038,0,604035304,1092">这是他喜欢的几个主播吗</d>
<d p="2501.3450,4,25,14893055,1773936041,0,12052692,1093">好孩子不玩米</d>
<d p="2501.3450,4,25,14893055,1773936041,0,34531495,1094">笑的</d>
<d p="2506.3790,4,25,14893055,1773936046,0,13429933,1095">[岁己收藏集表情包_哈哈]</d>
<d p="2506.3790,4,25,14893055,1773936047,0,227618,1096">米酥己</d>
<d p="2507.8410,4,25,16772431,1773936048,0,6606769,1097">[岁己收藏集表情包_哈哈]</d>
<d p="2512.8770,4,25,14893055,1773936053,0,227618,1098">[岁己收藏集表情包_妈呀]</d>
<d p="2514.1800,1,25,16777215,1773936055,0,339001,1099">啾咪啾</d>
<d p="2516.9380,1,25,16777215,1773936057,0,19929984,1100">有双重人格</d>
<d p="2518.2300,4,25,14893055,1773936057,0,288811455,1101">三个人。。。</d>
<d p="2519.5350,4,25,14893055,1773936059,0,266375,1102">[岁己收藏集表情包_哈哈]</d>
<d p="2525.8890,1,25,16777215,1773936066,0,8481710,1103">好爽</d>
<d p="2525.8890,4,25,14893055,1773936066,0,4184347,1104">干嘛，，，我没说这是我</d>
<d p="2527.3280,4,25,14893055,1773936067,0,13327599,1105">三个号正好三等分</d>
<d p="2527.3280,4,25,16772431,1773936067,0,6606769,1106">[岁己收藏集表情包_哈哈]</d>
<d p="2532.5300,4,25,14893055,1773936073,0,12052692,1107">心里还有这个家吗…</d>
<d p="2532.5300,4,25,14893055,1773936073,0,13327599,1108">哈哈他去哪玩了</d>
<d p="2534.9810,1,25,16777215,1773936075,0,8481710,1109">piapiapia</d>
<d p="2534.9810,4,25,14893055,1773936075,0,13429933,1110">晚安晚安</d>
<d p="2535.1230,4,25,14893055,1773936075,0,22389880,1111">[岁己收藏集表情包_凝视]</d>
<d p="2535.1230,4,25,14893055,1773936075,0,34531495,1112">每次梦到岁己醒来都得开心半天</d>
<d p="2536.2840,1,25,16777215,1773936076,0,2225137,1113">拜拜喵</d>
<d p="2537.7230,4,25,16772431,1773936077,0,6606769,1114">拜比拜比哦</d>
<d p="2537.7230,4,25,14893055,1773936078,0,258865753,1115">晚安哦 明天见</d>
<d p="2540.1680,4,25,14893055,1773936080,0,87078921,1116">晚安小岁</d>
<d p="2544.0690,4,25,14893055,1773936084,0,227618,1117">[岁己收藏集表情包_哈哈]</d>
<d p="2549.4170,4,25,14893055,1773936089,0,34531495,1118">[岁己收藏集表情包_哈哈]</d>
<d p="2549.4170,4,25,14893055,1773936090,0,9669499,1119">哈哈</d>
<d p="2554.4630,4,25,14893055,1773936095,0,4184347,1120">我觉得有人会这样</d>
<d p="2555.9140,4,25,14893055,1773936096,0,34531495,1121">拜拜</d>
<d p="2557.0530,4,25,14893055,1773936097,0,13429933,1122">晚安晚安，明天见</d>
<d p="2557.0530,1,25,16777215,1773936098,0,1578150211,1123">(￣3￣).</d>
<d p="2559.6520,4,25,14893055,1773936099,0,227618,1124">拜拜</d>
<d p="2559.8140,4,25,14893055,1773936100,0,9669499,1125">[岁己收藏集表情包_哈哈]</d>
<d p="2559.8140,4,25,14893055,1773936100,0,34531495,1126">会想你的</d>
<d p="2561.1110,4,25,16772431,1773936100,0,6606769,1127">拜比拜比</d>
<d p="2563.5810,4,25,14893055,1773936104,0,13429933,1128">拜拜～</d>
<d p="2564.8500,4,25,14893055,1773936105,0,604035304,1129">啊啊啊</d>
<d p="2565.0080,4,25,14893055,1773936105,0,34531495,1130">晚安</d>
<d p="2565.0080,1,25,16772431,1773936105,0,52194,1131">拜拜哦小岁~</d>
<d p="2567.6080,4,25,16772431,1773936107,0,6606769,1132">喜欢你</d>
<d p="2567.6080,4,25,14893055,1773936107,0,34531495,1133">拜拜</d>
<d p="2568.7670,1,25,16777215,1773936109,0,2225137,1134">晚安</d>
<d p="2568.9040,4,25,14893055,1773936109,0,22389880,1135">晚安</d>
<d p="2570.2020,4,25,14893055,1773936109,0,34531495,1136">明天见</d>
<d p="2571.5040,4,25,16772431,1773936111,0,6606769,1137">[岁己收藏集表情包_啵啵]</d>
<d p="2572.6710,4,25,14893055,1773936112,0,227618,1138">奈特奈特</d>
<d p="2573.9400,1,25,16777215,1773936114,0,339001,1139">啾咪啾</d>
<d p="2575.2830,4,25,14893055,1773936115,0,378855235,1140">拜拜</d>
</i>